Workbook

Sheet backup Portugal
A1: Empresa | B1: País | C1: Área | F1: Modelo SaaS ou tecnologia escalável com componente recorrente | J1: A seleção inicial das empresas foi realizada a partir de bases públicas amplamente utilizadas no mapeamento de ecossistemas de inovação, incluindo relatórios do Distrito (Brasil), Dealroom (Portugal), Startup Portugal e LinkedIn Company Directory.
A2: OutSystems | B2: Portugal | C2: DevTools / Low-Code | F2: Atuação predominante B2B
A3: Talkdesk | B3: Portugal | C3: CX / Contact Center | F3: Entre 20 e 500 colaboradores
A4: Feedzai | B4: Portugal | C4: Fintech / Fraud | F4: Pelo menos uma rodada de funding identificável
A5: Remote | B5: Portugal | C5: HRTech / Global Payroll | F5: Dados públicos disponíveis via LinkedIn e Crunchbase
A6: Sword Health | B6: Portugal | C6: HealthTech
A7: Unbabel | B7: Portugal | C7: AI / Language Tech | F7: Dealroom
A8: Defined.ai | B8: Portugal | C8: AI / Data | F8: Startup Portugal
A9: Infraspeak | B9: Portugal | C9: Facility Management SaaS | F9: Web Summit
A10: Codacy | B10: Portugal | C10: DevTools | F10: Distrito
A11: Jscrambler | B11: Portugal | C11: Cybersecurity
A12: Uniplaces | B12: Portugal | C12: PropTech
A13: Casafari | B13: Portugal | C13: PropTech / Data
A14: StudentFinance | B14: Portugal | C14: Fintech / EdFinance
A15: Probely | B15: Portugal | C15: Cybersecurity
A16: TonicApp | B16: Portugal | C16: HealthTech
A17: Rows | B17: Portugal | C17: Productivity SaaS
A18: Veniam | B18: Portugal | C18: Networking / Infra
A19: Blip | B19: Portugal | C19: Conversational Commerce
A20: Critical Software | B20: Portugal | C20: Enterprise Software
A21: Glintt | B21: Portugal | C21: HealthTech
A22: 360imprimir | B22: Portugal | C22: B2B Commerce SaaS
... A81: Clicksign | B81: Brazil | C81: Digital Signature

Sheet backup Brasil
A1: Organização | B1: Tipo de Finan. | C1: Funct. | D1: Indústrias (Resumo) | E1: Localização | F1: País | G1: CB Rank | H1: Data Últ. Finan. | I1: Status | J1: Total Captado | K1: Último Aporte | L1: Growth
A2: Bravium | B2: Venture | C2: 251-500 | D2: B2B, Loyalty, Analytics | E2: São Paulo | F2: Brasil | G2: 49895 | H2: 44817 | I2: — | J2: R$ 100M | K2: R$ 100M | L2: Low
A3: Moss.Earth | B3: Series A | C3: 51-100 | D3: Enviromental, Eng. | E3: São Paulo | F3: Brasil | G3: 50099 | H3: 44592 | I3: Early Stage Venture | J3: $13.4M | K3: $ 10M | L3: Low
A4: Doris | B4: Seed | C4: 11-50 | D4: Fashion, GenAI | E4: São Paulo | F4: Brasil | G4: 50105 | H4: 43983 | I4: Seed | J4: $10M | K4: $ 10M | L4: Low
A5: Loft | B5: Venture | C5: 1001-5k | D5: PropTech, FinTech | E5: São Paulo | F5: Brasil | G5: 50259 | H5: 45146 | I5: — | J5: $888M | K5: $ 100M | L5: Medium
A6: Yuca | B6: Series A | C6: 101-250 | D6: PropTech, Rental | E6: São Paulo | F6: Brasil | G6: 50484 | H6: 44369 | I6: Early Stage Venture | J6: $14.7M | K6: $ 10M | L6: Low
A7: Fintalk AI | B7: Venture | C7: 51-100 | D7: AI, Sales Auto. | E7: São Paulo | F7: Brasil | G7: 50570 | H7: 45776 | I7: — | J7: $ 3M | K7: R$ 6M | L7: Low
A8: Salú | B8: Seed | C8: 101-250 | D8: Health Care, SaaS | E8: São Paulo | F8: Brasil | G8: 50983 | H8: 44649 | I8: Seed | J8: R$ 12M | K8: R$ 12M | L8: Low
A9: Foxbit | B9: Series A | C9: 11-50 | D9: Crypto, FinTech | E9: São Paulo | F9: Brasil | G9: 50993 | H9: 44614 | I9: Early Stage Venture | J9: $21.1M | K9: $ 21M | L9: Low
A10: IBBX | B10: Venture | C10: 51-100 | D10: IoT, Energy Mgmt | E10: Capivari | F10: Brasil | G10: 51024 | H10: 44721 | I10: — | J10: $5M | K10: $ 5M | L10: Low
A11: Nomo | B11: Seed | C11: 51-100 | D11: Telecom, IT | E11: São Paulo | F11: Brasil | G11: 51432 | H11: 44511 | I11: M&A | J11: R$ 14M | K11: R$ 14M | L11: High
A12: Turn2C | B12: Series A | C12: 51-100 | D12: AI, Finance | E12: São Paulo | F12: Brasil | G12: 51440 | H12: 45354 | I12: Early Stage Venture | J12: R$ 33.5M | K12: R$ 25M | L12: High
A13: Clubbi | B13: Series A | C13: 101-250 | D13: B2B, RetailTech | E13: Rio de Jan. | F13: Brasil | G13: 51732 | H13: 44713 | I13: Early Stage Venture | J13: $17M | K13: $ 12M | L13: Low
... A39: unico IDtech | B39: Series D | C39: 501-1k | D39: Identity Mgmt | E39: São Paulo | F39: Brasil | G39: 55876 | H39: 44665 | I39: Late Stage Venture | J39: $336M | K39: $ 100M | L39: Low
A40: 3778 | B40: Venture | C40: 1001-5k | D40: HealthTech, Data | E40: Minas Gerais | F40: Brasil | G40: 56426 | H40: 44252 | I40: — | J40: R$ 200M | K40: R$ 200M | L40: Low
A41: Agilize | B41: Venture | C41: 101-250 | D41: Accounting, FinTech | E41: Salvador | F41: Brasil | G41: 56468 | H41: 45625 | I41: — | J41: $9M | K41: $ 9M | L41: High
A42: Neoenergia | B42: Post-IPO Debt | C42: 10k+ | D42: Renewable Energy | E42: Rio de Jan. | F42: Brasil | G42: 56547 | H42: 45839 | I42: IPO | J42: $ 735M | K42: € 300M | L42: Medium
A43: Kenlo | B43: Venture | C43: 101-250 | D43: PropTech, SaaS | E43: Campina | F43: Brasil | G43: 57140 | H43: 44417 | I43: — | J43: R$ 122M | K43: R$ 95M | L43: Low
A44: Vittude | B44: Series A | C44: 101-250 | D44: HealthTech, SaaS | E44: São Paulo | F44: Brasil | G44: 57486 | H44: 44635 | I44: Early Stage Venture | J44: $8.4M | K44: $ 7M | L44: Low
A45: SuaQuadra | B45: Seed | C45: 11-50 | D45: PropTech, Rental | E45: São Paulo | F45: Brasil | G45: 57496 | H45: 45104 | I45: Seed | J45: R$ 21M | K45: R$ 21M | L45: Low
A46: Gerdau | B46: Post-IPO Debt | C46: 10k+ | D46: Manufacturing, Steel | E46: São Paulo | F46: Brasil | G46: 57623 | H46: 45829 | I46: IPO | J46: R$ 566M | K46: R$ 566M | L46: Low
A47: Alinea Health | B47: Venture | C47: 11-50 | D47: HealthTech, Corp. | E47: São Paulo | F47: Brasil | G47: 57686 | H47: 44636 | I47: — | J47: R$ 21.3M | K47: R$ 20M | L47: Low
A48: Hi Platform | B48: Series A | C48: 101-250 | D48: AI, Customer Svc | E48: São Paulo | F48: Brasil | G48: 57780 | H48: 44469 | I48: Early Stage Venture | J48: R$ 35M | K48: R$ 35M | L48: Low
A49: FOOD TO SAVE | B49: Seed | C49: 51-100 | D49: Waste Mgmt, Food | E49: São Paulo | F49: Brasil | G49: 58000 | H49: 45211 | I49: Seed | J49: $3.7M | K49: $ 3.1M | L49: High
A50: Truth & Tales | B50: Seed | C50: 11-50 | D50: EdTech, Gaming | E50: Florianópolis | F50: Brasil | G50: 58069 | H50: 43353 | I50: Seed | J50: R$ 1.2M | K50: R$ 1.2M | L50: Low
A51: Psyche Aero. | B51: Venture | C51: 101-250 | D51: Aerospace, AgTech | E51: S. J. Campos | F51: Brasil | G51: 58366 | H51: 45589 | I51: — | J51: R$ 34.2M | K51: R$ 17M | L51: Low

Sheet Dados
B1: Nome da empresa | C1: País | D1: Cidade | E1: Ano de fundação | F1: Total HC | G1: Crescimento HC 12 meses | H1: Funcionários engenharia | I1: Funcionários vendas | J1: Funcionários marketing | K1: Funcionários CS | L1: Funding (USD) | M1: Número de rodadas | N1: Ano de ultima rodada | O1: Status de funding | P1: Growth score (métrica do próprio cb) | Q1: Funding/HC | R1: Tech/Sales rate | S1: Fundação até ult rodada | T1: Seguidores linkedin | U1: TEM IA | V1: Tendencia aumento de quadro ult 12m
A2: Crunchbase | B2: x | C2: x | D2: x | F2: x | L2: x | N2: x | O2: x | P2: x | Q2: =L1/F1 -> #VALUE! | R2: =I1/H1 -> #VALUE! | S2: =N2-E2 -> #VALUE!
A3: Linkedin | E3: x | H3: proxy | I3: proxy | J3: proxy
B6: 659 | C6: Oct 2, 2025 | D6: Late Stage Ventur

Sheet  Dataset - Bruto
A1: Organização | B1: Tipo de Finan. | C1: Funct. | D1: Indústrias (Resumo) | E1: Localização | F1: País | G1: CB Rank | H1: Data Últ. Finan. | I1: Status | J1: Total Captado | K1: Último Aporte | L1: Growth | M1: Faixa de vidas | O1: Funct. | P1: Brasil | Q1: Portugal
A2: Jáchegou | B2: Seed | C2: 11-50 | D2: Delivery, E-Commerce | E2: Porto | F2: Portugal | G2: 164.97 | H2: 44896 | I2: Seed | J2: 150 | K2: 50 | L2: Low | M2: =VLOOKUP(C2,Apoio!A:B,2,0) -> 11-50 | O2: 11-50 | P2: =COUNTIFS($F:$F,P$1,$M:$M,$O2,A:A,"<>"&"Seed") -> 59 | Q2: =COUNTIFS($F:$F,Q$1,$M:$M,$O2,B:B,"<>"&"Seed") -> 47 | T2: Empresas de 11 - 1000 funcionários
A3: PharmAssistant | B3: Seed | C3: 11-50 | D3: Health Tech, Hardware | E3: Lisboa | F3: Portugal | G3: 610.511 | H3: 41877 | I3: Seed | J3: 50 | K3: 50 | L3: Low | M3: =VLOOKUP(C3,Apoio!A:B,2,0) -> 11-50 | O3: 51-100 | P3: =COUNTIFS($F:$F,P$1,$M:$M,$O3,A:A,"<>"&"Seed") -> 31 | Q3: =COUNTIFS($F:$F,Q$1,$M:$M,$O3,B:B,"<>"&"Seed") -> 13 | T3: Passaram da fase seed
A4: Bandora | B4: Venture | C4: 11-50 | D4: AI, Smart Building | E4: Porto | F4: Portugal | G4: 9.616 | H4: 45832 | I4: — | J4: €2,135,383 | K4: 100 | L4: Low | M4: =VLOOKUP(C4,Apoio!A:B,2,0) -> 11-50 | O4: 101-250 | P4: =COUNTIFS($F:$F,P$1,$M:$M,$O4,A:A,"<>"&"Seed") -> 39 | Q4: =COUNTIFS($F:$F,Q$1,$M:$M,$O4,B:B,"<>"&"Seed") -> 4
A5: Wakaru | B5: Seed | C5: 11-50 | D5: Cyber Security, Analytics | E5: Torres V. | F5: Portugal | G5: 138.709 | H5: 44222 | I5: Seed | J5: 100 | K5: 100 | L5: Low | M5: =VLOOKUP(C5,Apoio!A:B,2,0) -> 11-50 | O5: 251-500 | P5: =COUNTIFS($F:$F,P$1,$M:$M,$O5,A:A,"<>"&"Seed") -> 16 | Q5: =COUNTIFS($F:$F,Q$1,$M:$M,$O5,B:B,"<>"&"Seed") -> 3
A6: Avenidas | B6: Venture | C6: 51-100 | D6: Mobility, Transportation | E6: Lisboa | F6: Portugal | G6: 167.71 | H6: 45027 | I6: — | J6: 100 | K6: 100 | L6: High | M6: =VLOOKUP(C6,Apoio!A:B,2,0) -> 51-100 | O6: 501-1000 | P6: =COUNTIFS($F:$F,P$1,$M:$M,$O6,A:A,"<>"&"Seed") -> 15 | Q6: =COUNTIFS($F:$F,Q$1,$M:$M,$O6,B:B,"<>"&"Seed") -> 3
A7: Ubiwhere | B7: Seed | C7: 11-50 | D7: Smart Cities, Software | E7: Barrocas | F7: Portugal | G7: 172.334 | H7: 43132 | I7: Seed | J7: 100 | K7: 100 | L7: Low | M7: =VLOOKUP(C7,Apoio!A:B,2,0) -> 11-50 | O7: 1k-5k | P7: =COUNTIFS($F:$F,P$1,$M:$M,$O7) -> 10 | Q7: =COUNTIFS($F:$F,Q$1,$M:$M,$O7) -> 1
A8: AQVA MORE | B8: Seed | C8: 11-50 | D8: Water Purification, Mfg | E8: Oeiras | F8: Portugal | G8: 191.396 | H8: 44187 | I8: Seed | J8: 100 | K8: 100 | L8: Low | M8: =VLOOKUP(C8,Apoio!A:B,2,0) -> 11-50 | O8: 5k-10k | P8: =COUNTIFS($F:$F,P$1,$M:$M,$O8) -> 3 | Q8: =COUNTIFS($F:$F,Q$1,$M:$M,$O8) -> 0
A9: Cuckuu | B9: Seed | C9: 11-50 | D9: Social Alarm, Mobile Apps | E9: Lisboa | F9: Portugal | G9: 204.915 | H9: 42706 | I9: Seed | J9: $1,164,772 | K9: 100 | L9: — | M9: =VLOOKUP(C9,Apoio!A:B,2,0) -> 11-50 | O9: 10k+ | P9: =COUNTIFS($F:$F,P$1,$M:$M,$O9) -> 8 | Q9: =COUNTIFS($F:$F,Q$1,$M:$M,$O9) -> 2
A10: YouClap | B10: Seed | C10: 11-50 | D10: Social Media, Challenges | E10: Ílhavo | F10: Portugal | G10: 213.296 | H10: 43082 | I10: Seed | J10: 150 | K10: 100 | L10: Low | M10: =VLOOKUP(C10,Apoio!A:B,2,0) -> 11-50
A11: S&DG Consulting | B11: Seed | C11: 11-50 | D11: Energy Storage, Renewable | E11: Coimbra | F11: Portugal | G11: 245.591 | H11: 44194 | I11: Seed | J11: 100 | K11: 100 | L11: — | M11: =VLOOKUP(C11,Apoio!A:B,2,0) -> 11-50 | O11: Total | P11: =SUM(P2:P9) -> 181 | Q11: =SUM(Q2:Q9) -> 73
A12: BladeInsight | B12: Seed | C12: 11-50 | D12: Drone Mgmt, Renewable | E12: Porto S. | F12: Portugal | G12: 93.591 | H12: 44265 | I12: Seed | J12: €2,118,536 | K12: 129.139 | L12: Low | M12: =VLOOKUP(C12,Apoio!A:B,2,0) -> 11-50
A13: Digital Works | B13: Seed | C13: 11-50 | D13: Digital Media, Software | E13: Lisboa | F13: Portugal | G13: 498.852 | H13: 41445 | I13: Seed | J13: 150 | K13: 150 | L13: Low | M13: =VLOOKUP(C13,Apoio!A:B,2,0) -> 11-50
A14: Merytu | B14: Seed | C14: 11-50 | D14: Employment, Mobile Apps | E14: Lisboa | F14: Portugal | G14: 142.155 | H14: 44294 | I14: Seed | J14: 200 | K14: 200 | L14: Low | M14: =VLOOKUP(C14,Apoio!A:B,2,0) -> 11-50
A15: MagniFinance | B15: Seed | C15: 11-50 | D15: Fintech, Cashflow Mgmt | E15: Lisboa | F15: Portugal | G15: 633.519 | H15: 42064 | I15: Seed | J15: 200 | K15: 200 | L15: Low | M15: =VLOOKUP(C15,Apoio!A:B,2,0) -> 11-50 | O15: 11 - 500 | P15: =SUM(P2:P5) -> 145 | Q15: =SUM(Q2:Q5) -> 67
A16: PLUX biosignals | B16: Seed | C16: 11-50 | D16: Medical Device, Wireless | E16: Arruda V. | F16: Portugal | G16: 535.279 | H16: 41548 | I16: Seed | J16: 730 | K16: 230 | L16: Low | M16: =VLOOKUP(C16,Apoio!A:B,2,0) -> 11-50
A17: Mission To Escape | B17: Seed | C17: 11-50 | D17: Casual Games, Ent. | E17: Lisboa | F17: Portugal | G17: 184.569 | H17: 44985 | I17: Seed | J17: 250 | K17: 250 | L17: Low | M17: =VLOOKUP(C17,Apoio!A:B,2,0) -> 11-50
A18: Streambolico | B18: Seed | C18: 11-50 | D18: Video Streaming, Wireless | E18: Porto | F18: Portugal | G18: 3,671,559 | H18: 42339 | I18: M&A | J18: €1,250,000 | K18: 250 | L18: — | M18: =VLOOKUP(C18,Apoio!A:B,2,0) -> 11-50
A19: Dig. Manager Guru | B19: Seed | C19: 11-50 | D19: Sales Mgmt, Retail Tech | E19: Santarém | F19: Portugal | G19: 140.658 | H19: 43524 | I19: Seed | J19: 300 | K19: 300 | L19: Low | M19: =VLOOKUP(C19,Apoio!A:B,2,0) -> 11-50
A20: GFoundry | B20: Seed | C20: 11-50 | D20: HR Tech, Gamification | E20: Matosinhos | F20: Portugal | G20: 416.447 | H20: 41820 | I20: Seed | J20: 300 | K20: 300 | L20: Low | M20: =VLOOKUP(C20,Apoio!A:B,2,0) -> 11-50
A21: GrowIN Portugal | B21: Seed | C21: 11-50 | D21: Fintech, SaaS, Legal Tech | E21: Faro | F21: Portugal | G21: 168.628 | H21: 43415 | I21: Seed | J21: 450 | K21: 450 | L21: Low | M21: =VLOOKUP(C21,Apoio!A:B,2,0) -> 11-50
A22: Sled | B22: Seed | C22: 11-50 | D22: FinTech, Payments | E22: Curitiba | F22: Brasil | G22: 102.173 | H22: 44596 | I22: Seed | J22: R$7,500,000 | K22: 500 | L22: Low | M22: =VLOOKUP(C22,Apoio!A:B,2,0) -> 11-50
A23: BioMimetx | B23: Seed | C23: 501-1000 | D23: Biotech, Biofuel | E23: Coimbra | F23: Portugal | G23: 116.484 | H23: 44918 | I23: Seed | J23: €3,700,000 | K23: 500 | L23: Low | M23: =VLOOKUP(C23,Apoio!A:B,2,0) -> 501-1000
A24: Infinite Foundry | B24: Seed | C24: 11-50 | D24: 3D, Industrial VR | E24: Porto | F24: Portugal | G24: 120.094 | H24: 43451 | I24: Seed | J24: 500 | K24: 500 | L24: Low | M24: =VLOOKUP(C24,Apoio!A:B,2,0) -> 11-50
A25: X-Plora | B25: Seed | C25: 11-50 | D25: AR, XR, Tourism Tech | E25: Porto | F25: Portugal | G25: 151.616 | H25: 43731 | I25: Seed | J25: 500 | K25: 500 | L25: Low | M25: =VLOOKUP(C25,Apoio!A:B,2,0) -> 11-50
A26: Logical Safety | B26: Seed | C26: 11-50 | D26: IoT Safety, Predictive | E26: Leiria | F26: Portugal | G26: 217.882 | H26: 43501 | I26: Seed | J26: 500 | K26: 500 | L26: — | M26: =VLOOKUP(C26,Apoio!A:B,2,0) -> 11-50
A27: beamian | B27: Seed | C27: 11-50 | D27: Event Tech, IoT, NFC | E27: Porto | F27: Portugal | G27: 133.518 | H27: 43646 | I27: Seed | J27: 800 | K27: 600 | L27: Low | M27: =VLOOKUP(C27,Apoio!A:B,2,0) -> 11-50
A28: Bitcliq | B28: Seed | C28: 11-50 | D28: Blockchain, IoT, Fishing | E28: Caldas R. | F28: Portugal | G28: 151.726 | H28: 43504 | I28: Seed | J28: 600 | K28: 600 | L28: Low | M28: =VLOOKUP(C28,Apoio!A:B,2,0) -> 11-50
A29: B-PARTS.com | B29: Seed | C29: 11-50 | D29: Automotive E-Comm | E29: Porto | F29: Portugal | G29: 314.538 | H29: 41830 | I29: M&A | J29: 650 | K29: 650 | L29: Low | M29: =VLOOKUP(C29,Apoio!A:B,2,0) -> 11-50
A30: InKlusion | B30: Seed | C30: 11-50 | D30: Software, 3D Design | E30: Covilhã | F30: Portugal | G30: 168.544 | H30: 44864 | I30: Seed | J30: 700 | K30: 700 | L30: Low | M30: =VLOOKUP(C30,Apoio!A:B,2,0) -> 11-50
A31: Whizztek | B31: Seed | C31: 11-50 | D31: Sports Social Network | E31: Porto | F31: Portugal | G31: 1,142,007 | H31: 41817 | I31: Seed | J31: 750 | K31: 750 | L31: — | M31: =VLOOKUP(C31,Apoio!A:B,2,0) -> 11-50
A32: Treat U | B32: Seed | C32: 11-50 | D32: Biotech, Nanotech | E32: Leiria | F32: Portugal | G32: 3,070,907 | H32: 41480 | I32: M&A | J32: 760 | K32: 760 | L32: — | M32: =VLOOKUP(C32,Apoio!A:B,2,0) -> 11-50
A33: SocialTalk | B33: Seed | C33: 11-50 | D33: Influencer Marketing | E33: Lisboa | F33: Portugal | G33: 109.458 | H33: 44797 | I33: Seed | J33: 770 | K33: 770 | L33: Low | M33: =VLOOKUP(C33,Apoio!A:B,2,0) -> 11-50
A34: DocDigitizer | B34: Seed | C34: 11-50 | D34: Cognitive AI, SaaS | E34: Lisboa | F34: Portugal | G34: 97.413 | H34: 44454 | I34: Seed | J34: €1,190,000 | K34: 800 | L34: Low | M34: =VLOOKUP(C34,Apoio!A:B,2,0) -> 11-50
A35: Codavel | B35: Seed | C35: 11-50 | D35: App Performance, CDN | E35: Porto | F35: Portugal | G35: 127.886 | H35: 44470 | I35: Seed | J35: €2,900,000 | K35: 900 | L35: Low | M35: =VLOOKUP(C35,Apoio!A:B,2,0) -> 11-50
A36: ChemiTek | B36: Seed | C36: 11-50 | D36: Solar Panel Maintenance | E36: Esposende | F36: Portugal | G36: — | H36: — | I36: — | J36: — | K36: — | L36: — | M36: =VLOOKUP(C36,Apoio!A:B,2,0) -> 11-50
A37: Sabesp | B37: Post-IPO Debt | C37: 10001+ | D37: Sanitation | E37: São Paulo | F37: Brasil | G37: 49319 | H37: 46049 | I37: IPO | J37: $2.5B | K37: $ 1.5B | L37: Low | M37: =VLOOKUP(C37,Apoio!A:B,2,0) -> 10k+
A38: Pitzi | B38: Series D | C38: 101-250 | D38: InsurTech | E38: Osasco | F38: Brasil | G38: 46204 | H38: 43773 | I38: Late Stage Venture | J38: $29.7M | K38: $ 10.3M | L38: Low | M38: =VLOOKUP(C38,Apoio!A:B,2,0) -> 101-250
A39: Delend | B39: Seed | C39: 51-100 | D39: FinTech, SaaS | E39: São Paulo | F39: Brasil | G39: 41566 | H39: 45379 | I39: Seed | J39: $20.1M | K39: $ 10M | L39: Medium | M39: =VLOOKUP(C39,Apoio!A:B,2,0) -> 51-100
A40: Dolado | B40: Series A | C40: 51-100 | D40: B2B, Marketplace | E40: São Paulo | F40: Brasil | G40: 42072 | H40: 44656 | I40: Early Stage Venture | J40: $12.2M | K40: $ 10M | L40: Low | M40: =VLOOKUP(C40,Apoio!A:B,2,0) -> 51-100
A41: The Coffee | B41: Venture | C41: 101-250 | D41: Food & Beverage | E41: Curitiba | F41: Brasil | G41: 45946 | H41: 45229 | I41: — | J41: $30.5M | K41: $ 10M | L41: Low | M41: =VLOOKUP(C41,Apoio!A:B,2,0) -> 101-250
A42: Farmtech | B42: Venture | C42: 101-250 | D42: Asset Mgmt, Agri | E42: São Paulo | F42: Brasil | G42: 48582 | H42: 45483 | I42: — | J42: $10M | K42: $ 10M | L42: High | M42: =VLOOKUP(C42,Apoio!A:B,2,0) -> 101-250
A43: Monkey | B43: Series B | C43: 101-250 | D43: FinTech, Finance | E43: São Paulo | F43: Brasil | G43: 41518 | H43: 45485 | I43: Early Stage Venture | J43: $19.6M | K43: $ 12.1M | L43: High | M43: =VLOOKUP(C43,Apoio!A:B,2,0) -> 101-250
A44: Gravia | B44: Series E | C44: 251-500 | D44: Construction | E44: Taguatinga | F44: Brasil | G44: 42363 | H44: 44756 | I44: Late Stage Venture | J44: $149.1M | K44: $ 15M | L44: Low | M44: =VLOOKUP(C44,Apoio!A:B,2,0) -> 251-500
A45: Zak | B45: Series A | C45: 101-250 | D45: FinTech, Food | E45: São Paulo | F45: Brasil | G45: 45433 | H45: 44510 | I45: Early Stage Venture | J45: $15M | K45: $ 15M | L45: Low | M45: =VLOOKUP(C45,Apoio!A:B,2,0) -> 101-250
A46: Quanto | B46: Series A | C46: 101-250 | D46: Open Banking | E46: São Paulo | F46: Brasil | G46: 49328 | H46: 44091 | I46: Early Stage Venture | J46: $20M | K46: $ 15M | L46: Low | M46: =VLOOKUP(C46,Apoio!A:B,2,0) -> 101-250
A47: Liquid | B47: Seed | C47: 11-50 | D47: AI, PropTech | E47: São Paulo | F47: Brasil | G47: 44278 | H47: 45839 | I47: Seed | J47: $2.1M | K47: $ 2.1M | L47: Low | M47: =VLOOKUP(C47,Apoio!A:B,2,0) -> 11-50
A48: deco.cx | B48: Seed | C48: 11-50 | D48: DevTools, E-com | E48: Rio de Jan. | F48: Brasil | G48: 43447 | H48: 45300 | I48: Seed | J48: $2.7M | K48: $ 2.2M | L48: Low | M48: =VLOOKUP(C48,Apoio!A:B,2,0) -> 11-50
... A80: Genial Care | B80: Venture | C80: 101-250 | D80: HealthTech, Autism | E80: São Paulo | F80: Brasil | G80: 32.044 | H80: 45316 | I80: — | J80: $31,005,209 | K80: $10,000,000 | L80: Low | M80: =VLOOKUP(C80,Apoio!A:B,2,0) -> 101-250
A81: ParaRede | B81: Venture | C81: 251-500 | D81: E-Commerce, Marketplace | E81: Lisboa | F81: Portugal | G81: 1,266,521 | H81: 36766 | I81: — | J81: $10,000,000 | K81: $10,000,000 | L81: High | M81: =VLOOKUP(C81,Apoio!A:B,2,0) -> 251-500
A82: Kamino | B82: Series A | C82: 51-100 | D82: Financial OS, AI | E82: São Paulo | F82: Brasil | G82: 2.657 | H82: 45909 | I82: Early | J82: $20,170,000 | K82: $10,120,000 | L82: Med | M82: =VLOOKUP(C82,Apoio!A:B,2,0) -> 51-100
A83: Flash | B83: Series C | C83: 501-1000 | D83: Employee Benefits | E83: São Paulo | F83: Brasil | G83: 13.98 | H83: 44629 | I83: Late | J83: $130,000,000 | K83: $100,000,000 | L83: Low | M83: =VLOOKUP(C83,Apoio!A:B,2,0) -> 501-1000
A84: Banco do Brasil | B84: Post-IPO | C84: 10k+ | D84: Banking | E84: Brasília | F84: Brasil | G84: 33.157 | H84: 45925 | I84: IPO | J84: $1.23B | K84: $100,000,000 | L84: Low | M84: =VLOOKUP(C84,Apoio!A:B,2,0) -> 10k+
A85: Pismo | B85: Series B | C85: 501-1k | D85: Core Banking, PaaS | E85: São Paulo | F85: Brasil | G85: 15.997 | H85: 44488 | I85: M&A | J85: $118,000,000 | K85: $108,000,000 | L85: Low | M85: =VLOOKUP(C85,Apoio!A:B,2,0) -> 501-1000
A86: Creditas | B86: Series G | C86: 1k-5k | D86: FinTech, Lending | E86: São Paulo | F86: Brasil | G86: 17.009 | H86: 45992 | I86: Late | J86: $1.22B | K86: $108,000,000 | L86: High | M86: =VLOOKUP(C86,Apoio!A:B,2,0) -> 1k-5k
A87: DuelNow | B87: Seed | C87: 11-50 | D87: Sports Betting, Gambling | E87: Lisboa | F87: Portugal | G87: 48.457 | H87: 45505 | I87: Seed | J87: $11,000,000 | K87: $11,000,000 | L87: Low | M87: =VLOOKUP(C87,Apoio!A:B,2,0) -> 11-50
A88: BotCity | B88: Series A | C88: 51-100 | D88: RPA, GenAI | E88: São Paulo | F88: Brasil | G88: 24.504 | H88: 45925 | I88: Early | J88: $15,000,000 | K88: $12,000,000 | L88: Med | M88: =VLOOKUP(C88,Apoio!A:B,2,0) -> 51-100
A89: BotCity | B89: Series A | C89: 51-100 | D89: RPA, GenAI | E89: São Paulo | F89: Brasil | G89: 24.504 | H89: 45925 | I89: Early | J89: $15,000,000 | K89: $12,000,000 | L89: Med | M89: =VLOOKUP(C89,Apoio!A:B,2,0) -> 51-100
A90: Nutrium | B90: Series A | C90: 11-50 | D90: Health, Nutrition | E90: Braga | F90: Portugal | G90: 21.012 | H90: 45916 | I90: Early | J90: $19,935,543 | K90: $12,000,000 | L90: Med | M90: =VLOOKUP(C90,Apoio!A:B,2,0) -> 11-50
A91: Stratio | B91: Series A | C91: 51-100 | D91: Fleet Management | E91: Lisboa | F91: Portugal | G91: 33.102 | H91: 44529 | I91: Early | J91: $15,365,459 | K91: $12,000,000 | L91: Low | M91: =VLOOKUP(C91,Apoio!A:B,2,0) -> 51-100
A92: PlatformE | B92: Series B | C92: 11-50 | D92: Fashion Tech, 3D, MTO | E92: Porto | F92: Portugal | G92: 71.905 | H92: 43766 | I92: Early | J92: $16,635,985 | K92: $12,000,000 | L92: Low | M92: =VLOOKUP(C92,Apoio!A:B,2,0) -> 11-50
A93: Gringo | B93: Series C | C93: 251-500 | D93: Car App, Fintech | E93: São Paulo | F93: Brasil | G93: 19.436 | H93: 45544 | I93: M&A | J93: $90,268,052 | K93: $12,500,000 | L93: High | M93: =VLOOKUP(C93,Apoio!A:B,2,0) -> 251-500
A94: GuestU | B94: Seed | C94: 11-50 | D94: Hospitality Tech, IoT | E94: Lisboa | F94: Portugal | G94: 206.217 | H94: 42987 | I94: M&A | J94: $3,204,643 | K94: $120,000 | L94: — | M94: =VLOOKUP(C94,Apoio!A:B,2,0) -> 11-50
A95: MeshApp | B95: Seed | C95: 11-50 | D95: Mobile, Dev Tools | E95: Lisboa | F95: Portugal | G95: 3,984,685 | H95: 41579 | I95: Seed | J95: $375,000 | K95: $125,000 | L95: — | M95: =VLOOKUP(C95,Apoio!A:B,2,0) -> 11-50
A96: Celcoin | B96: Series C | C96: 251-500 | D96: FinTech, Payments | E96: Barueri | F96: Brasil | G96: 4.475 | H96: 45461 | I96: Late | J96: $156,130,284 | K96: $125,000,000 | L96: Low | M96: =VLOOKUP(C96,Apoio!A:B,2,0) -> 251-500
A97: Trigger.Systems | B97: Seed | C97: 11-50 | D97: Agriculture Tech | E97: Lisboa | F97: Portugal | G97: 142.876 | H97: 43753 | I97: Seed | J97: $130,000 | K97: $130,000 | L97: Med | M97: =VLOOKUP(C97,Apoio!A:B,2,0) -> 11-50
A98: Musa | B98: Series A | C98: 101-250 | D98: Waste Mgmt, B2B | E98: São Paulo | F98: Brasil | G98: 12.397 | H98: 44470 | I98: Early | J98: $18,500,000 | K98: $15,000,000 | L98: High | M98: =VLOOKUP(C98,Apoio!A:B,2,0) -> 101-250
A99: Codacy | B99: Series B | C99: 51-100 | D99: Dev Tools, SaaS | E99: Lisboa | F99: Portugal | G99: 12.519 | H99: 44825 | I99: Early | J99: $29,400,000 | K99: $15,000,000 | L99: Low | M99: =VLOOKUP(C99,Apoio!A:B,2,0) -> 51-100
A100: BTG Pactual | B100: Post-IPO | C100: 5k-10k | D100: Banking, Asset Mgmt | E100: São Paulo | F100: Brasil | G100: 3.788 | H100: 45851 | I100: IPO | J100: $2.67B | K100: $160,000,000 | L100: High | M100: =VLOOKUP(C100,Apoio!A:B,2,0) -> 5k-10k
A101: NeoSpace AI | B101: Venture | C101: 11-50 | D101: FinTech, AI | E101: Uberlândia | F101: Brasil | G101: 33.914 | H101: 45685 | I101: — | J101: $18,000,000 | K101: $18,000,000 | L101: Low | M101: =VLOOKUP(C101,Apoio!A:B,2,0) -> 11-50
A102: iMotion | B102: Venture | C102: 11-50 | D102: Dev Tools, EDA | E102: Lisboa | F102: Portugal | G102: 312.966 | H102: 41723 | I102: — | J102: $18,500,000 | K102: $18,500,000 | L102: Low | M102: =VLOOKUP(C102,Apoio!A:B,2,0) -> 11-50
A103: Databox | B103: Seed | C103: 101-250 | D103: IT Distribution, Hardware | E103: Massamá | F103: Portugal | G103: 2,213,005 | H103: 41142 | I103: Seed | J103: $180,000 | K103: $180,000 | L103: Low | M103: =VLOOKUP(C103,Apoio!A:B,2,0) -> 101-250
A104: Olist | B104: Series E | C104: 501-1000 | D104: E-Commerce Enabler | E104: Curitiba | F104: Brasil | G104: 11.344 | H104: 44545 | I104: Late | J104: $322,485,000 | K104: $186,000,000 | L104: Low | M104: =VLOOKUP(C104,Apoio!A:B,2,0) -> 501-1000
A105: MadeiraMadeira | B105: Series E | C105: 1k-5k | D105: E-Commerce, Home | E105: Curitiba | F105: Brasil | G105: 18.996 | H105: 44203 | I105: Late | J105: $338,820,267 | K105: $190,000,000 | L105: Low | M105: =VLOOKUP(C105,Apoio!A:B,2,0) -> 1k-5k
A106: Arado | B106: Series B | C106: 101-250 | D106: AgTech, Supply Chain | E106: São Paulo | F106: Brasil | G106: 28.488 | H106: 45625 | I106: Early | J106: $21,370,375 | K106: $2,000,000 | L106: High | M106: =VLOOKUP(C106,Apoio!A:B,2,0) -> 101-250
A107: Polygon | B107: Series A | C107: 11-50 | D107: Biometrics, IT Services | E107: Porto | F107: Portugal | G107: 114.998 | H107: 43983 | I107: Early | J107: $2,200,000 | K107: $2,200,000 | L107: Low | M107: =VLOOKUP(C107,Apoio!A:B,2,0) -> 11-50
A108: e-Schooling | B108: Venture | C108: 11-50 | D108: EdTech, Apps | E108: Braga | F108: Portugal | G108: 128.406 | H108: 43466 | I108: — | J108: $2,200,000 | K108: $2,200,000 | L108: Low | M108: =VLOOKUP(C108,Apoio!A:B,2,0) -> 11-50
A109: STAGE | B109: Seed | C109: 11-50 | D109: Music, Internet | E109: Lisboa | F109: Portugal | G109: 45.018 | H109: 45457 | I109: Seed | J109: $2,400,000 | K109: $2,400,000 | L109: High | M109: =VLOOKUP(C109,Apoio!A:B,2,0) -> 11-50
A110: 180 Seguros | B110: Venture | C110: 101-250 | D110: InsurTech | E110: São Paulo | F110: Brasil | G110: 13.618 | H110: 45953 | I110: — | J110: $51,118,155 | K110: $2,500,000 | L110: Med | M110: =VLOOKUP(C110,Apoio!A:B,2,0) -> 101-250
A111: Traive | B111: Series B | C111: 51-100 | D111: AgFintech, GenAI | E111: São Paulo | F111: Brasil | G111: 17.576 | H111: 45324 | I111: Early | J111: $50,800,000 | K111: $20,000,000 | L111: Low | M111: =VLOOKUP(C111,Apoio!A:B,2,0) -> 51-100
A112: VELVET | B112: Venture | C112: 11-50 | D112: VC Liquidity | E112: São Paulo | F112: Brasil | G112: 10.461 | H112: 44602 | I112: — | J112: $203,500,000 | K112: $200,000,000 | L112: High | M112: =VLOOKUP(C112,Apoio!A:B,2,0) -> 11-50
A113: UME | B113: Series B | C113: 101-250 | D113: FinTech, Credit | E113: São Paulo | F113: Brasil | G113: 25.804 | H113: 45908 | I113: Early | J113: $86,290,928 | K113: $21,000,000 | L113: Med | M113: =VLOOKUP(C113,Apoio!A:B,2,0) -> 101-250
A114: Unbabel | B114: Venture | C114: 251-500 | D114: AI, Translation | E114: Lisboa | F114: Portugal | G114: 12.812 | H114: 45281 | I114: M&A | J114: $112,180,004 | K114: $21,000,000 | L114: Med | M114: =VLOOKUP(C114,Apoio!A:B,2,0) -> 251-500
A115: Alice | B115: Series C | C115: 251-500 | D115: Health Insurance | E115: São Paulo | F115: Brasil | G115: 3.003 | H115: 45699 | I115: Late | J115: $216,300,000 | K115: $22,000,000 | L115: High | M115: =VLOOKUP(C115,Apoio!A:B,2,0) -> 251-500
... A129: pleez | B129: Venture | C129: 11-50 | D129: FoodTech, Data | E129: Lisboa | F129: Portugal | G129: 44.17 | H129: 45602 | I129: — | J129: $6,970,906 | K129: $3,000,000 | L129: High | M129: =VLOOKUP(C129,Apoio!A:B,2,0) -> 11-50
A130: FiberSensing | B130: Venture | C130: 11-50 | D130: Analytics, Hardware | E130: Maia | F130: Portugal | G130: 3,472,483 | H130: 39092 | I130: M&A | J130: $3,110,000 | K130: $3,110,000 | L130: — | M130: =VLOOKUP(C130,Apoio!A:B,2,0) -> 11-50
A131: Virtuleap | B131: Seed | C131: 11-50 | D131: Health Tech, VR, Neuroscience | E131: Lisboa | F131: Portugal | G131: 48.18 | H131: 44927 | I131: Seed | J131: $4,904,500 | K131: $3,300,000 | L131: Low | M131: =VLOOKUP(C131,Apoio!A:B,2,0) -> 11-50
A132: Lumx | B132: Seed | C132: 11-50 | D132: Web3, Stablecoins | E132: Rio de Jan. | F132: Brasil | G132: 40.074 | H132: 45945 | I132: Seed | J132: $3,400,000 | K132: $3,400,000 | L132: Med | M132: =VLOOKUP(C132,Apoio!A:B,2,0) -> 11-50
A133: JBS | B133: Post-IPO | C133: 10k+ | D133: Food Processing | E133: São Paulo | F133: Brasil | G133: 9.566 | H133: 45831 | I133: IPO | J133: $7.75B | K133: $3.5B | L133: High | M133: =VLOOKUP(C133,Apoio!A:B,2,0) -> 10k+
A134: Kanastra | B134: Series B | C134: 101-250 | D134: Alternative Inv. | E134: Uberlândia | F134: Brasil | G134: 13.547 | H134: 45931 | I134: Early | J134: $63,748,062 | K134: $30,000,000 | L134: Med | M134: =VLOOKUP(C134,Apoio!A:B,2,0) -> 101-250
A135: Mombak | B135: Series A | C135: 51-100 | D135: Carbon Removal | E135: São Paulo | F135: Brasil | G135: 13.885 | H135: 45776 | I135: Early | J135: $149,788,405 | K135: $30,000,000 | L135: Low | M135: =VLOOKUP(C135,Apoio!A:B,2,0) -> 51-100
A136: Ethena | B136: Venture | C136: 11-50 | D136: Blockchain, DeFi | E136: Lisboa | F136: Portugal | G136: 3.462 | H136: 45931 | I136: — | J136: $206,820,000 | K136: $30,000,000 | L136: High | M136: =VLOOKUP(C136,Apoio!A:B,2,0) -> 11-50
A137: HDF | B137: Seed | C137: 11-50 | D137: Product Design, Furniture | E137: Lisboa | F137: Portugal | G137: 3,827,386 | H137: 41737 | I137: Seed | J137: $30,400 | K137: $30,400 | L137: — | M137: =VLOOKUP(C137,Apoio!A:B,2,0) -> 11-50
A138: Azos | B138: Series B | C138: 101-250 | D138: InsurTech | E138: São Paulo | F138: Brasil | G138: 19.999 | H138: 45707 | I138: Early | J138: $48,766,670 | K138: $30,500,000 | L138: High | M138: =VLOOKUP(C138,Apoio!A:B,2,0) -> 101-250
A139: Akurateco | B139: Seed | C139: 51-100 | D139: Payments, SaaS | E139: Santarém | F139: Portugal | G139: 11.102 | H139: 45078 | I139: Seed | J139: $406,400 | K139: $300,000 | L139: Med | M139: =VLOOKUP(C139,Apoio!A:B,2,0) -> 51-100
A140: Azul SA | B140: Post-IPO | C140: 10k+ | D140: Airlines | E140: Barueri | F140: Brasil | G140: 13.942 | H140: 46071 | I140: IPO | J140: $3.56B | K140: $300,000,000 | L140: Med | M140: =VLOOKUP(C140,Apoio!A:B,2,0) -> 10k+
A141: IO5 Networks | B141: Series A | C141: 11-50 | D141: IoT, Network Hardware | E141: Lisboa | F141: Portugal | G141: 96.816 | H141: 44691 | I141: Early | J141: $32,700,000 | K141: $31,000,000 | L141: — | M141: =VLOOKUP(C141,Apoio!A:B,2,0) -> 11-50
A142: ArchVentures SA | B142: Seed | C142: 11-50 | D142: 3D Printing, FinTech | E142: Faro | F142: Portugal | G142: 3,326,355 | H142: 41875 | I142: Seed | J142: $328,000 | K142: $328,000 | L142: — | M142: =VLOOKUP(C142,Apoio!A:B,2,0) -> 11-50
A143: Enter | B143: Series A | C143: 11-50 | D143: Legal Tech, AI | E143: São Paulo | F143: Brasil | G143: 5.905 | H143: 45923 | I143: Early | J143: $40,500,000 | K143: $35,000,000 | L143: High | M143: =VLOOKUP(C143,Apoio!A:B,2,0) -> 11-50
A144: GuestCentric | B144: Venture | C144: 51-100 | D144: Hotel Ecommerce, Travel | E144: Lisboa | F144: Portugal | G144: 324.007 | H144: 40008 | I144: — | J144: $5,250,000 | K144: $4,000,000 | L144: Med | M144: =VLOOKUP(C144,Apoio!A:B,2,0) -> 51-100
...

Sheet Dataset - Ajustado
A1: Organização | B1: Tipo de Finan. | C1: Indústrias (Resumo) | D1: Localização | E1: País | F1: Data Últ. Finan. | G1: Status | H1: Total Captado | I1: Último Aporte | J1: Growth | K1: Funcionários (linkedin) | L1: Faixa de vidas | M1: Fundação | N1: Site | O1: Remover | P1: Seguidores Linkedin | Q1: Tem IA?
A2: Jáchegou | B2: Seed | C2: Delivery, E-Commerce | D2: Porto | E2: Portugal | F2: 44896 | G2: Seed | H2: 162000 | I2: 54000 | J2: Low | L2: 11 - 50 | O2: x
A3: PharmAssistant | B3: Seed | C3: Health Tech, Hardware | D3: Lisboa | E3: Portugal | F3: 41877 | G3: Seed | H3: 54000 | I3: 54000 | J3: Low | L3: 11 - 50 | O3: x
A4: Bandora | B4: Venture | C4: AI, Smart Building | D4: Porto | E4: Portugal | F4: 45832 | G4: — | H4: 2306214 | I4: 108000 | J4: Low | K4: 31 | L4: 11 - 50 | M4: 2017 | N4: http://www.bandorasystems.com
A5: Wakaru | B5: Seed | C5: Cyber Security, Analytics | D5: Torres V. | E5: Portugal | F5: 44222 | G5: Seed | H5: 108000 | I5: 108000 | J5: Low | L5: 11 - 50 | O5: x
A6: Avenidas | B6: Venture | C6: Mobility, Transportation | D6: Lisboa | E6: Portugal | F6: 45027 | G6: — | H6: 108000 | I6: 108000 | J6: High | K6: 169 | L6: 101 - 250 | M6: 2016 | N6: http://www.avenidas.pt
A7: Ubiwhere | B7: Seed | C7: Smart Cities, Software | D7: Barrocas | E7: Portugal | F7: 43132 | G7: Seed | H7: 108000 | I7: 108000 | J7: Low | K7: 57 | L7: 51 - 100 | M7: 2007 | N7: http://www.ubiwhere.com
A8: AQVA MORE | B8: Seed | C8: Water Purification, Mfg | D8: Oeiras | E8: Portugal | F8: 44187 | G8: Seed | H8: 108000 | I8: 108000 | J8: Low | L8: 11 - 50 | O8: x
A9: Cuckuu | B9: Seed | C9: Social Alarm, Mobile Apps | D9: Lisboa | E9: Portugal | F9: 42706 | G9: Seed | H9: 1164772 | I9: 108000 | J9: — | L9: 11 - 50 | N9: https://cuckuu.com | O9: x
A10: YouClap | B10: Seed | C10: Social Media, Challenges | D10: Ílhavo | E10: Portugal | F10: 43082 | G10: Seed | H10: 162000 | I10: 108000 | J10: Low | L10: 11 - 50 | O10: x
A11: S&DG Consulting | B11: Seed | C11: Energy Storage, Renewable | D11: Coimbra | E11: Portugal | F11: 44194 | G11: Seed | H11: 108000 | I11: 108000 | J11: — | L11: 11 - 50 | O11: x
A12: BladeInsight | B12: Seed | C12: Drone Mgmt, Renewable | D12: Porto S. | E12: Portugal | F12: 44265 | G12: Seed | H12: 2288019 | I12: 139471 | J12: Low | L12: 11 - 50 | N12: http://www.bladeinsight.com | O12: x
A13: Digital Works | B13: Seed | C13: Digital Media, Software | D13: Lisboa | E13: Portugal | F13: 41445 | G13: Seed | H13: 162000 | I13: 162000 | J13: Low | L13: 11 - 50 | M13: 2021 | N13: https://digitalworkssolution.com | O13: x
A14: Merytu | B14: Seed | C14: Employment, Mobile Apps | D14: Lisboa | E14: Portugal | F14: 44294 | G14: Seed | H14: 216000 | I14: 216000 | J14: Low | L14: 11 - 50 | M14: 2019 | N14: https://merytu.com/
A15: MagniFinance | B15: Seed | C15: Fintech, Cashflow Mgmt | D15: Lisboa | E15: Portugal | F15: 42064 | G15: Seed | H15: 216000 | I15: 216000 | J15: Low | L15: 11 - 50 | M15: 2015 | N15: http://www.magnifinance.com
A16: PLUX biosignals | B16: Seed | C16: Medical Device, Wireless | D16: Arruda V. | E16: Portugal | F16: 41548 | G16: Seed | H16: 788400 | I16: 248400 | J16: Low | K16: 35 | L16: 11 - 50 | M16: 2007 | N16: http://www.pluxbiosignals.com
A17: Mission To Escape | B17: Seed | C17: Casual Games, Ent. | D17: Lisboa | E17: Portugal | F17: 44985 | G17: Seed | H17: 270000 | I17: 270000 | J17: Low | K17: 29 | L17: 11 - 50 | M17: 2015 | N17: http://www.missiontoescape.com | O17: x
A18: Streambolico | B18: Seed | C18: Video Streaming, Wireless | D18: Porto | E18: Portugal | F18: 42339 | G18: M&A | H18: 1350000 | I18: 270000 | J18: — | L18: 11 - 50 | O18: x
A19: Dig. Manager Guru | B19: Seed | C19: Sales Mgmt, Retail Tech | D19: Santarém | E19: Portugal | F19: 43524 | G19: Seed | H19: 324000 | I19: 324000 | J19: Low | K19: 47 | L19: 11 - 50 | M19: 2017 | N19: https://digitalmanager.guru
A20: GFoundry | B20: Seed | C20: HR Tech, Gamification | D20: Matosinhos | E20: Portugal | F20: 41820 | G20: Seed | H20: 324000 | I20: 324000 | J20: Low | K20: 4 | L20: 2 - 10 | M20: 2014 | N20: http://gfoundry.com
A21: GrowIN Portugal | B21: Seed | C21: Fintech, SaaS, Legal Tech | D21: Faro | E21: Portugal | F21: 43415 | G21: Seed | H21: 486000 | I21: 486000 | J21: Low | L21: 11 - 50 | M21: 2018 | N21: http://www.growinportugal.com | O21: x
A22: Sled | B22: Seed | C22: FinTech, Payments | D22: Curitiba | E22: Brasil | F22: 44596 | G22: Seed | H22: 1350000 | I22: 540000 | J22: Low | L22: 11 - 50 | O22: x
A23: BioMimetx | B23: Seed | C23: Biotech, Biofuel | D23: Coimbra | E23: Portugal | F23: 44918 | G23: Seed | H23: 3996000 | I23: 540000 | J23: Low | K23: 8 | L23: 2 - 10 | M23: 2013 | N23: https://www.biomimetx.com/
A24: Infinite Foundry | B24: Seed | C24: 3D, Industrial VR | D24: Porto | E24: Portugal | F24: 43451 | G24: Seed | H24: 540000 | I24: 540000 | J24: Low | K24: 35 | L24: 11 - 50 | M24: 2017 | N24: https://www.infinitefoundry.com/
A25: X-Plora | B25: Seed | C25: AR, XR, Tourism Tech | D25: Porto | E25: Portugal | F25: 43731 | G25: Seed | H25: 540000 | I25: 540000 | J25: Low | L25: 11 - 50 | O25: x
A26: Logical Safety | B26: Seed | C26: IoT Safety, Predictive | D26: Leiria | E26: Portugal | F26: 43501 | G26: Seed | H26: 540000 | I26: 540000 | J26: — | L26: 11 - 50 | O26: x
A27: beamian | B27: Seed | C27: Event Tech, IoT, NFC | D27: Porto | E27: Portugal | F27: 43646 | G27: Seed | H27: 864000 | I27: 648000 | J27: Low | L27: 11 - 50 | M27: 2019 | N27: http://beamian.com
A28: Bitcliq | B28: Seed | C28: Blockchain, IoT, Fishing | D28: Caldas R. | E28: Portugal | F28: 43504 | G28: Seed | H28: 648000 | I28: 648000 | J28: Low | L28: 11 - 50 | M28: 2013 | N28: http://www.bitcliq.com
A29: B-PARTS | B29: Seed | C29: Automotive E-Comm | D29: Porto | E29: Portugal | F29: 41830 | G29: M&A | H29: 702000 | I29: 702000 | J29: Low | K29: 70 | L29: 51 - 100 | M29: 2013 | N29: https://www.b-parts.com
A30: InKlusion | B30: Seed | C30: Software, 3D Design | D30: Covilhã | E30: Portugal | F30: 44864 | G30: Seed | H30: 756000 | I30: 756000 | J30: Low | L30: 11 - 50 | M30: 2013 | N30: https://inklusion.pt
A31: Whizztek | B31: Seed | C31: Sports Social Network | D31: Porto | E31: Portugal | F31: 41817 | G31: Seed | H31: 810000 | I31: 810000 | J31: — | L31: 11 - 50 | M31: 2012 | O31: x
A32: Treat U | B32: Seed | C32: Biotech, Nanotech | D32: Leiria | E32: Portugal | F32: 41480 | G32: M&A | H32: 820800 | I32: 820800 | J32: — | L32: 11 - 50 | O32: x
A33: SocialTalk | B33: Seed | C33: Influencer Marketing | D33: Lisboa | E33: Portugal | F33: 44797 | G33: Seed | H33: 831600 | I33: 831600 | J33: Low | L33: 11 - 50 | M33: 2021 | N33: https://socialtalk.io
A34: DocDigitizer | B34: Seed | C34: Cognitive AI, SaaS | D34: Lisboa | E34: Portugal | F34: 44454 | G34: Seed | H34: 1285200 | I34: 864000 | J34: Low | L34: 11 - 50 | M34: 2017 | N34: https://www.docdigitizer.com/
A35: Codavel | B35: Seed | C35: App Performance, CDN | D35: Porto | E35: Portugal | F35: 44470 | G35: Seed | H35: 3132000 | I35: 972000 | J35: Low | L35: 11 - 50 | M35: 2018 | N35: https://www.codavel.com/
A36: ChemiTek | B36: Seed | C36: Solar Panel Maintenance | D36: Esposende | E36: Portugal | F36: — | G36: — | H36: — | I36: — | J36: — | L36: 11 - 50 | O36: x
A37: Sabesp | B37: Post-IPO Debt | C37: Sanitation | D37: São Paulo | E37: Brasil | F37: 46049 | G37: IPO | H37: 2500000000 | I37: 1500000000 | J37: Low | L37: 10000 - + | O37: x
A38: Pitzi | B38: Series D | C38: InsurTech | D38: Osasco | E38: Brasil | F38: 43773 | G38: Late Stage Venture | H38: 29700000 | I38: 10300000 | J38: Low | K38: 177 | L38: 101 - 250 | M38: 2012 | N38: http://www.pitzi.com.br
A39: Delend | B39: Seed | C39: FinTech, SaaS | D39: São Paulo | E39: Brasil | F39: 45379 | G39: Seed | H39: 20100000 | I39: 10000000 | J39: Medium | L39: 51 - 100 | M39: 2023 | N39: https://www.delend.finance/
A40: Dolado | B40: Series A | C40: B2B, Marketplace | D40: São Paulo | E40: Brasil | F40: 44656 | G40: Early Stage Venture | H40: 12200000 | I40: 10000000 | J40: Low | K40: 68 | L40: 51 - 100 | M40: 2020 | N40: http://dolado.com.br
A41: The Coffee | B41: Venture | C41: Food & Beverage | D41: Curitiba | E41: Brasil | F41: 45229 | G41: — | H41: 30500000 | I41: 10000000 | J41: Low | L41: 101 - 250 | O41: x
A42: Farmtech | B42: Venture | C42: Asset Mgmt, Agri | D42: São Paulo | E42: Brasil | F42: 45483 | G42: — | H42: 10000000 | I42: 10000000 | J42: High | K42: 191 | L42: 101 - 250 | M42: 2017 | N42: https://farmtech.com.br/
A43: Monkey | B43: Series B | C43: FinTech, Finance | D43: São Paulo | E43: Brasil | F43: 45485 | G43: Early Stage Venture | H43: 19600000 | I43: 12100000 | J43: High | L43: 101 - 250 | M43: 2016 | N43: https://www.monkey.tech
A44: Gravia | B44: Series E | C44: Construction | D44: Taguatinga | E44: Brasil | F44: 44756 | G44: Late Stage Venture | H44: 149100000 | I44: 15000000 | J44: Low | L44: 251 - 500 | O44: x
A45: Zak | B45: Series A | C45: FinTech, Food | D45: São Paulo | E45: Brasil | F45: 44510 | G45: Early Stage Venture | H45: 15000000 | I45: 15000000 | J45: Low | K45: 176 | L45: 101 - 250 | M45: 2018 | N45: https://www.zak.app/
A46: Quanto | B46: Series A | C46: Open Banking | D46: São Paulo | E46: Brasil | F46: 44091 | G46: Early Stage Venture | H46: 20000000 | I46: 15000000 | J46: Low | K46: 141 | L46: 101 - 250 | M46: 2016 | N46: quan.to
A47: Liquid | B47: Seed | C47: AI, PropTech | D47: São Paulo | E47: Brasil | F47: 45839 | G47: Seed | H47: 2100000 | I47: 2100000 | J47: Low | L47: 11 - 50 | O47: x
A48: deco.cx | B48: Seed | C48: DevTools, E-com | D48: Rio de Jan. | E48: Brasil | F48: 45300 | G48: Seed | H48: 2700000 | I48: 2200000 | J48: Low | L48: 11 - 50 | O48: x
A49: Aravita | B49: Seed | C49: AI, AgTech | D49: São Paulo | E49: Brasil | F49: 45015 | G49: Seed | H49: 2500000 | I49: 2500000 | J49: Low | K49: 17 | L49: 11 - 50 | M49: 2022 | N49: https://www.aravita.com/
A50: Visio.ai | B50: Seed | C50: AI, Comp. Vision | D50: São Paulo | E50: Brasil | F50: 45363 | G50: Seed | H50: 2500000 | I50: 2500000 | J50: Low | K50: 68 | L50: 51 - 100 | M50: 2021 | N50: https://www.visio.ai/
A51: Sallve | B51: Series B | C51: Beauty, D2C | D51: São Paulo | E51: Brasil | F51: 44312 | G51: Early Stage Venture | H51: 31700000 | I51: 20000000 | J51: Low | L51: 101 - 250 | O51: x
A52: NovaDAX | B52: Series A | C52: Crypto, Trading | D52: São Paulo | E52: Brasil | F52: 43229 | G52: Early Stage Venture | H52: 20000000 | I52: 20000000 | J52: Low | K52: 29 | L52: 11 - 50 | M52: 2018 | N52: https://www.novadax.com.br/
A53: Akad Seguros | B53: Series A | C53: InsurTech | D53: São Paulo | E53: Brasil | F53: 45385 | G53: Early Stage Venture | H53: 22500000 | I53: 22500000 | J53: Low | L53: 101 - 250 | O53: x
A54: Portão 3 | B54: Seed | C54: Travel Mgmt | D54: Uberlândia | E54: Brasil | F54: 44944 | G54: Seed | H54: 3700000 | I54: 3600000 | J54: Low | K54: 3 | L54: 11 - 50 | M54: 2020 | N54: https://portao3.com.br
A55: Voa Health | B55: Seed | C55: AI, HealthTech | D55: Curitiba | E55: Brasil | F55: 45740 | G55: Seed | H55: 3200000 | I55: 3000000 | J55: High | K55: 27 | L55: 11 - 50 | M55: 2023 | N55: https://voa.health
A56: Accountfy | B56: Series A | C56: SaaS, Fin. Mgmt | D56: São Paulo | E56: Brasil | F56: 44364 | G56: Early Stage Venture | H56: 11000000 | I56: 4500000 | J56: Low | K56: 312 | L56: 251 - 500 | M56: 2017 | N56: https://www.accountfy.com/
A57: Sympla | B57: Venture | C57: Events, Ticketing | D57: B. Horizonte | E57: Brasil | F57: 43069 | G57: — | H57: 8800000 | I57: 4800000 | J57: Low | K57: 458 | L57: 251 - 500 | M57: 2012 | N57: https://produtores.sympla.com.br/
A58: Frente | B58: Series A | C58: FinTech, FX | D58: São Paulo | E58: Brasil | F58: 45825 | G58: Early Stage Venture | H58: 6000000 | I58: 5500000 | J58: High | K58: 265 | L58: 251 - 500 | M58: 2018 | N58: https://frentecorretora.com.br/
A59: Avante | B59: Venture | C59: FinTech, Credit | D59: São Paulo | E59: Brasil | F59: 44622 | G59: — | H59: 24600000 | I59: 5800000 | J59: Low | L59: 51 - 100 | O59: x
A60: Assis | B60: Seed | C60: AI Assistant | D60: São Paulo | E60: Brasil | F60: 45020 | G60: Seed | H60: 5000000 | I60: 5000000 | J60: Low | L60: 11 - 50 | O60: x
A61: Click Cash | B61: Venture | C61: Lending, Big Data | D61: São Paulo | E61: Brasil | F61: 44616 | G61: — | H61: 14300000 | I61: 6000000 | J61: Low | K61: 12 | L61: 11 - 50 | M61: 2019 | O61: x
A62: Destaxa | B62: Seed | C62: FinTech, Payments | D62: São Paulo | E62: Brasil | F62: 45254 | G62: Seed | H62: 10300000 | I62: 6000000 | J62: High | K62: 37 | L62: 51 - 100 | M62: 2021 | N62: https://destaxa.com.br/
A63: Konsi | B63: Seed | C63: FinTech, Payroll Loans | D63: Bahia | E63: Brasil | F63: 45467 | G63: Seed | H63: 1611770 | I63: 1000000 | J63: Low | K63: 178 | L63: 101 - 250 | M63: 2021 | N63: https://www.konsi.com.br/
A64: Beegol | B64: Venture | C64: AI, Telecom | D64: São Paulo | E64: Brasil | F64: 45632 | G64: — | H64: 5600000 | I64: 1000000 | J64: High | K64: 60 | L64: 51 - 100 | M64: 2019 | N64: https://www.beegol.com/
A65: Culttivo | B65: Series A | C65: AgTech, Coffee Credit | D65: São Paulo | E65: Brasil | F65: 45981 | G65: Early | H65: 16547191 | I65: 1000000 | J65: Med | K65: 68 | L65: 51 - 100 | M65: 2020 | N65: http://www.culttivo.com
A66: Fasqon | B66: Seed | C66: FinTech, Neobank, Web3 | D66: Funchal | E66: Portugal | F66: 45352 | G66: Seed | H66: 1300000 | I66: 1000000 | J66: Med | L66: 11 - 50 | M66: 2023 | N66: https://fasqon.com/
A67: Albato | B67: Seed | C67: No-code, Automation, SaaS | D67: Setúbal | E67: Portugal | F67: 44197 | G67: Seed | H67: 1000000 | I67: 1000000 | J67: Med | L67: 51 - 100 | M67: 2019 | N67: https://albato.com/
A68: Itau Unibanco | B68: Post-IPO | C68: Banking | D68: São Paulo | E68: Brasil | F68: 45715 | G68: M&A | H68: 1000000000 | I68: 1000000000 | J68: Med | L68: 10000 - + | O68: x
A69: Codavel (2) | B69: Seed | C69: Video CDN, Application Perf | D69: Porto | E69: Portugal | F69: 44501 | G69: Seed | H69: 3298430 | I69: 1043455 | J69: Low | L69: 11 - 50 | M69: 2018 | N69: https://www.codavel.com/
A70: GigU | B70: Venture | C70: Gig Economy, AI | D70: Rio de Jan. | E70: Brasil | F70: 45355 | G70: — | H70: 1200000 | I70: 1200000 | J70: Med | K70: 27 | L70: 11 - 50 | M70: 2017 | N70: https://www.gigu.app/br
A71: Saasuma | B71: Seed | C71: Cloud Search Tool | D71: Lisboa | E71: Portugal | F71: 44078 | G71: Seed | H71: 1250000 | I71: 1250000 | J71: Low | L71: 11 - 50 | M71: 2015 | N71: https://saasuma.com/
A72: Latitud | B72: Seed | C72: VC, Community | D72: São Paulo | E72: Brasil | F72: 44754 | G72: Seed | H72: 14500000 | I72: 1500000 | J72: Med | L72: 11 - 50 | O72: x
A73: Adv. Cyclone Sys | B73: Venture | C73: Mechanical Eng, Mfg | D73: Porto | E73: Portugal | F73: 39814 | G73: — | H73: 1500000 | I73: 1500000 | J73: Med | L73: 11 - 50 | N73: https://www.advancedcyclonesystems.com/ | O73: x
A74: impactMarket | B74: Seed | C74: Blockchain, Web3, FinTech | D74: Braga | E74: Portugal | F74: 44587 | G74: Seed | H74: 2100000 | I74: 1600000 | J74: Low | L74: 11 - 50 | O74: x
A75: SeaForester | B75: Seed | C75: Environmental Eng, Social | D75: Estoril | E75: Portugal | F75: 45954 | G75: Seed | H75: 1900000 | I75: 1900000 | J75: High | L75: 11 - 50 | O75: x
A76: UbiRider | B76: Seed | C76: Fintech, SaaS | D76: Porto | E76: Portugal | F76: 45355 | G76: Seed | H76: 1950000 | I76: 1950000 | J76: Low | K76: 23 | L76: 11 - 50 | M76: 2018 | N76: https://ubirider.com/
A77: Sami | B77: Series B | C77: Health Tech | D77: São Paulo | E77: Brasil | F77: 45643 | G77: Early | H77: 66231000 | I77: 10000000 | J77: High | K77: 497 | L77: 251 - 500 | M77: 2018 | N77: https://www.samisaude.com.br/
A78: BHub | B78: Series A | C78: AI Accountant, SaaS | D78: São Paulo | E78: Brasil | F78: 45988 | G78: Early | H78: 56421560 | I78: 10000000 | J78: High | K78: 641 | L78: 501 - 1000 | M78: 2021 | N78: https://bhub.com/
A79: dr.consulta | B79: Series D | C79: HealthTech | D79: São Paulo | E79: Brasil | F79: 45153 | G79: Late | H79: 178601756 | I79: 10000000 | J79: Low | K79: 1296 | L79: 1000 - 5000 | M79: 2011 | N79: http://www.drconsulta.com
A80: Genial Care | B80: Venture | C80: HealthTech, Autism | D80: São Paulo | E80: Brasil | F80: 45316 | G80: — | H80: 31005209 | I80: 10000000 | J80: Low | K80: 265 | L80: 251 - 500 | M80: 2020 | N80: https://genialcare.com.br/
A81: Kamino | B81: Series A | C81: Financial OS, AI | D81: São Paulo | E81: Brasil | F81: 45909 | G81: Early | H81: 20170000 | I81: 10120000 | J81: Med | K81: 169 | L81: 51 - 100 | M81: 2021 | N81: https://kamino.com.br/
A82: Flash | B82: Series C | C82: Employee Benefits | D82: São Paulo | E82: Brasil | F82: 44629 | G82: Late | H82: 130000000 | I82: 100000000 | J82: Low | L82: 501 - 1000 | M82: 2018 | N82: https://flashapp.com.br/
A83: Banco do Brasil | B83: Post-IPO | C83: Banking | D83: Brasília | E83: Brasil | F83: 45925 | G83: IPO | H83: 1230000000 | I83: 100000000 | J83: Low | L83: 10000 - + | O83: x
A84: Pismo | B84: Series B | C84: Core Banking, PaaS | D84: São Paulo | E84: Brasil | F84: 44488 | G84: M&A | H84: 118000000 | I84: 108000000 | J84: Low | K84: 567 | L84: 501 - 1000 | M84: 2016 | N84: https://www.pismo.io/
A85: Creditas | B85: Series G | C85: FinTech, Lending | D85: São Paulo | E85: Brasil | F85: 45992 | G85: Late | H85: 1220000000 | I85: 108000000 | J85: High | K85: 2157 | L85: 1000 - 5000 | M85: 2012 | N85: https://www.creditas.com/
A86: DuelNow | B86: Seed | C86: Sports Betting, Gambling | D86: Lisboa | E86: Portugal | F86: 45505 | G86: Seed | H86: 11000000 | I86: 11000000 | J86: Low | L86: 11 - 50 | M86: 2023 | N86: https://duelnow.com/
A87: BotCity | B87: Series A | C87: RPA, GenAI | D87: São Paulo | E87: Brasil | F87: 45925 | G87: Early | H87: 15000000 | I87: 12000000 | J87: Med | K87: 54 | L87: 51 - 100 | M87: 2018 | N87: https://botcity.dev/
A88: Nutrium | B88: Series A | C88: Health, Nutrition | D88: Braga | E88: Portugal | F88: 45916 | G88: Early | H88: 19935543 | I88: 12000000 | J88: Med | K88: 190 | L88: 101 - 250 | M88: 2015 | N88: https://nutrium.com/
A89: Stratio | B89: Series A | C89: Fleet Management | D89: Lisboa | E89: Portugal | F89: 44529 | G89: Early | H89: 15365459 | I89: 12000000 | J89: Low | K89: 68 | L89: 51 - 100 | M89: 2017 | N89: https://stratioautomotive.com/
A90: PlatformE | B90: Series B | C90: Fashion Tech, 3D, MTO | D90: Porto | E90: Portugal | F90: 43766 | G90: Early | H90: 16635985 | I90: 12000000 | J90: Low | K90: 40 | L90: 11 - 50 | M90: 2016 | N90: http://www.platforme.com
A91: Gringo | B91: Series C | C91: Car App, Fintech | D91: São Paulo | E91: Brasil | F91: 45544 | G91: M&A | H91: 90268052 | I91: 12500000 | J91: High | K91: 131 | L91: 251 - 500 | M91: 2019 | N91: https://gringo.com.vc/
A92: Nonius | B92: Venture | C92: Cloud Infrastructure | D92: Maia | E92: Portugal | F92: 42987 | G92: M&A | H92: 12960000 | I92: 11880000 | J92: — | K92: 239 | L92: 101 - 250 | M92: 2025 | N92: https://noniussolutions.com/
A93: MeshApp | B93: Seed | C93: Mobile, Dev Tools | D93: Lisboa | E93: Portugal | F93: 41579 | G93: Seed | H93: 375000 | I93: 125000 | J93: — | L93: 11 - 50 | M93: 2013 | O93: x
A94: Celcoin | B94: Series C | C94: FinTech, Payments | D94: Barueri | E94: Brasil | F94: 45461 | G94: Late | H94: 156130284 | I94: 125000000 | J94: Low | K94: 409 | L94: 251 - 500 | M94: 2016 | N94: https://www.celcoin.com.br/
A95: Trigger.Systems | B95: Seed | C95: Agriculture Tech | D95: Lisboa | E95: Portugal | F95: 43753 | G95: Seed | H95: 130000 | I95: 130000 | J95: Med | L95: 11 - 50 | M95: 2017 | N95: https://trigger.systems/
A96: Musa | B96: Series A | C96: Waste Mgmt, B2B | D96: São Paulo | E96: Brasil | F96: 44470 | G96: Early | H96: 18500000 | I96: 15000000 | J96: High | K96: 342 | L96: 251 - 500 | M96: 2019 | N96: https://www.musa.co/
A97: Codacy | B97: Series B | C97: Dev Tools, SaaS | D97: Lisboa | E97: Portugal | F97: 44825 | G97: Early | H97: 29400000 | I97: 15000000 | J97: Low | K97: 68 | L97: 51 - 100 | M97: 2012 | N97: https://www.codacy.com/
A98: BTG Pactual | B98: Post-IPO | C98: Banking, Asset Mgmt | D98: São Paulo | E98: Brasil | F98: 45851 | G98: IPO | H98: 2670000000 | I98: 160000000 | J98: High | L98: 5000 - 1000 | O98: x
A99: NeoSpace AI | B99: Venture | C99: FinTech, AI | D99: Uberlândia | E99: Brasil | F99: 45685 | G99: — | H99: 18000000 | I99: 18000000 | J99: Low | K99: 76 | L99: 51 - 100 | M99: 2023 | N99: https://www.neospace.ai/
A100: iMotion | B100: Venture | C100: Dev Tools, EDA | D100: Lisboa | E100: Portugal | F100: 41723 | G100: — | H100: 18500000 | I100: 18500000 | J100: Low | K100: 52 | L100: 51 - 100 | M100: 2006 | N100: https://imotion.pt/ | O100: x
...

Sheet Dataset 
A1: Organização | B1: Tipo de Finan. | C1: Indústrias (Resumo) | D1: País | E1: Data Últ. Finan. | F1: Total Captado | G1: Último Aporte | H1: Funcionários (linkedin) | I1: Faixa de vidas | J1: Fundação | K1: Site | L1: Seguidores Linkedin | M1: Tem IA? | N1: Momentum (%captado/captado total) | O1: Faturamento estimado | P1: Score Deeptech | Q1: Score Cloud Native | R1: Score DevTools | S1: Score Analytics | T1: Score Growth Stack | U1: Modelo de negócio
A2: AIDigitalEngine | B2: Seed | C2: Generative AI, RPA, Software | D2: Portugal | E2: 45168 | F2: 103000 | G2: 65000 | H2: 10 | I2: 11 - 50 | J2: 2021 | K2: https://www.ai-digitalengine.com/ | N2: =G2/F2 -> 0.63106796 | P2: 0 | Q2: 1 | R2: 0 | S2: 0 | T2: 0 | U2: Unknown
A3: Bandora | B3: Venture | C3: AI, Smart Building | D3: Portugal | E3: 45832 | F3: 2306214 | G3: 108000 | H3: 31 | I3: 11 - 50 | J3: 2017 | K3: http://www.bandorasystems.com | N3: =G3/F3 -> 0.046829999 | P3: 1 | Q3: 0 | R3: 1 | S3: 0 | T3: 2 | U3: B2B
A4: Avenidas | B4: Venture | C4: Mobility, Transportation | D4: Portugal | E4: 45027 | F4: 108000 | G4: 108000 | H4: 169 | I4: 101 - 250 | J4: 2016 | K4: http://www.avenidas.pt | N4: =G4/F4 -> 1 | O4: 6000000 | P4: 0 | Q4: 1 | R4: 0 | S4: 0 | T4: 1 | U4: B2B2C
A5: Ubiwhere | B5: Seed | C5: Smart Cities, Software | D5: Portugal | E5: 43132 | F5: 108000 | G5: 108000 | H5: 57 | I5: 51 - 100 | J5: 2007 | K5: http://www.ubiwhere.com | N5: =G5/F5 -> 1 | O5: 2000000 | P5: 2 | Q5: 2 | R5: 1 | S5: 1 | T5: 1 | U5: B2B
A6: Trigger.Systems | B6: Seed | C6: Agriculture Tech | D6: Portugal | E6: 43753 | F6: 130000 | G6: 130000 | H6: 9 | I6: 2 - 10 | J6: 2017 | K6: https://trigger.systems/ | N6: =G6/F6 -> 1 | P6: 0 | Q6: 1 | R6: 1 | S6: 0 | T6: 1 | U6: B2B
A7: Merytu | B7: Seed | C7: Employment, Mobile Apps | D7: Portugal | E7: 44294 | F7: 216000 | G7: 216000 | H7: 34 | I7: 11 - 50 | J7: 2019 | K7: https://merytu.com/ | N7: =G7/F7 -> 1 | P7: 0 | Q7: 0 | R7: 0 | S7: 1 | T7: 1 | U7: B2C
A8: MagniFinance | B8: Seed | C8: Fintech, Cashflow Mgmt | D8: Portugal | E8: 42064 | F8: 216000 | G8: 216000 | H8: 5 | I8: 11 - 50 | J8: 2015 | K8: http://www.magnifinance.com | N8: =G8/F8 -> 1 | O8: 322000 | P8: 0 | Q8: 0 | R8: 0 | S8: 1 | T8: 6 | U8: B2B
A9: PLUX biosignals | B9: Seed | C9: Medical Device, Wireless | D9: Portugal | E9: 41548 | F9: 788400 | G9: 248400 | H9: 35 | I9: 11 - 50 | J9: 2007 | K9: http://www.pluxbiosignals.com | N9: =G9/F9 -> 0.31506849 | O9: 2948000 | P9: 0 | Q9: 0 | R9: 1 | S9: 1 | T9: 4 | U9: B2C
A10: GeoInovaAI | B10: Seed | C10: AgTech, Computer Vision | D10: Brasil | E10: 45667 | F10: 300000 | G10: 250000 | H10: 10 | I10: 2 - 10 | J10: 2024 | K10: https://geoinova.com.br/ | N10: =G10/F10 -> 0.83333333 | P10: 1 | Q10: 1 | R10: 1 | S10: 2 | T10: 1 | U10: B2B
A11: Akurateco | B11: Seed | C11: Payments, SaaS | D11: Portugal | E11: 45078 | F11: 406400 | G11: 300000 | H11: 61 | I11: 51 - 100 | J11: 2019 | K11: https://akurateco.com/ | N11: =G11/F11 -> 0.73818898 | P11: 1 | Q11: 5 | R11: 6 | S11: 0 | T11: 4 | U11: Unknown
A12: Dig. Manager Guru | B12: Seed | C12: Sales Mgmt, Retail Tech | D12: Portugal | E12: 43524 | F12: 324000 | G12: 324000 | H12: 47 | I12: 11 - 50 | J12: 2017 | K12: https://digitalmanager.guru | N12: =G12/F12 -> 1 | P12: 0 | Q12: 0 | R12: 0 | S12: 1 | T12: 3 | U12: B2B2C
A13: GFoundry | B13: Seed | C13: HR Tech, Gamification | D13: Portugal | E13: 41820 | F13: 324000 | G13: 324000 | H13: 4 | I13: 2 - 10 | J13: 2014 | K13: http://gfoundry.com | N13: =G13/F13 -> 1 | P13: 1 | Q13: 0 | R13: 1 | S13: 0 | T13: 1 | U13: B2B
A14: Pink App | B14: Seed | C14: Collaboration, SaaS | D14: Brasil | E14: 43831 | F14: 735093 | G14: 400000 | H14: 19 | I14: 11 - 50 | J14: 2019 | K14: https://www.pinkapp.com/ | N14: =G14/F14 -> 0.54414884 | P14: 0 | Q14: 1 | R14: 0 | S14: 2 | T14: 0 | U14: B2B
A15: BlueMetrics | B15: Venture | C15: AI, Data Analytics | D15: Brasil | E15: 46077 | F15: 1021880 | G15: 486000 | H15: 56 | I15: 51 - 100 | J15: 2016 | K15: https://www.bluemetrics.ai/ | N15: =G15/F15 -> 0.475594 | P15: 1 | Q15: 4 | R15: 4 | S15: 1 | T15: 3 | U15: B2B
A16: Mobmio | B16: Series A | C16: Mobile Marketing | D16: Portugal | E16: 45311 | F16: 500000 | G16: 500000 | H16: 10 | I16: 2 - 10 | J16: 2023 | K16: https://mobmio.com/ | N16: =G16/F16 -> 1 | P16: 0 | Q16: 1 | R16: 0 | S16: 0 | T16: 2 | U16: B2C
A17: BioMimetx | B17: Seed | C17: Biotech, Biofuel | D17: Portugal | E17: 44918 | F17: 3996000 | G17: 540000 | H17: 8 | I17: 2 - 10 | J17: 2013 | K17: https://www.biomimetx.com/ | N17: =G17/F17 -> 0.13513514 | P17: 1 | Q17: 0 | R17: 0 | S17: 0 | T17: 0 | U17: B2B
A18: Infinite Foundry | B18: Seed | C18: 3D, Industrial VR | D18: Portugal | E18: 43451 | F18: 540000 | G18: 540000 | H18: 35 | I18: 11 - 50 | J18: 2017 | K18: https://www.infinitefoundry.com/ | N18: =G18/F18 -> 1 | P18: 1 | Q18: 1 | R18: 0 | S18: 0 | T18: 0 | U18: B2B
A19: Novvo | B19: Seed | C19: Wellness, Consumer | D19: Brasil | E19: 45623 | F19: 576000 | G19: 576000 | H19: 22 | I19: 11 - 50 | J19: 2022 | K19: https://novvo.com.br/ | N19: =G19/F19 -> 1 | P19: 1 | Q19: 0 | R19: 0 | S19: 0 | T19: 3 | U19: B2C
A20: Monest | B20: Venture | C20: Asset Recovery | D20: Brasil | E20: 45708 | F20: 576000 | G20: 576000 | H20: 97 | I20: 51 - 100 | J20: 2017 | K20: https://monest.com.br/ | N20: =G20/F20 -> 1 | P20: 1 | Q20: 1 | R20: 1 | S20: 2 | T20: 2 | U20: B2B2C
A21: beamian | B21: Seed | C21: Event Tech, IoT, NFC | D21: Portugal | E21: 43646 | F21: 864000 | G21: 648000 | H21: 7 | I21: 2 - 10 | J21: 2019 | K21: http://beamian.com | N21: =G21/F21 -> 0.75 | P21: 0 | Q21: 0 | R21: 1 | S21: 1 | T21: 3 | U21: B2C
... A24: B-PARTS | B24: Seed | C24: Automotive E-Comm | D24: Portugal | E24: 41830 | F24: 702000 | G24: 702000 | H24: 70 | I24: 51 - 100 | J24: 2013 | K24: https://www.b-parts.com | N24: =G24/F24 -> 1 | P24: 0 | Q24: 1 | R24: 0 | S24: 3 | T24: 4 | U24: B2C
A25: VOLL | B25: Seed | C25: Business Travel | D25: Brasil | E25: 43993 | F25: 720000 | G25: 720000 | H25: 649 | I25: 501 - 1000 | J25: 2017 | K25: https://www.govoll.com/ | N25: =G25/F25 -> 1 | O25: 151000000 | P25: 0 | Q25: 3 | R25: 4 | S25: 2 | T25: 5 | U25: Unknown
A26: Stattus4 | B26: Seed | C26: CleanTech, Water | D26: Brasil | E26: 45413 | F26: 1524198 | G26: 727363 | H26: 31 | I26: 11 - 50 | J26: 2014 | K26: https://stattus4.com/ | N26: =G26/F26 -> 0.47721031 | P26: 1 | Q26: 0 | R26: 3 | S26: 0 | T26: 0 | U26: B2B
A27: NOMADX | B27: Seed | C27: Travel, Marketplace | D27: Portugal | E27: 43861 | F27: 1000000 | G27: 750000 | H27: 7 | I27: 2 - 10 | J27: 2017 | K27: http://nomadx.com/ | N27: =G27/F27 -> 0.75 | P27: 0 | Q27: 0 | R27: 0 | S27: 1 | T27: 1 | U27: B2C
A28: InKlusion | B28: Seed | C28: Software, 3D Design | D28: Portugal | E28: 44864 | F28: 756000 | G28: 756000 | H28: 5 | I28: 2 - 10 | J28: 2013 | K28: https://inklusion.pt | N28: =G28/F28 -> 1 | O28: 377000 | P28: 2 | Q28: 0 | R28: 1 | S28: 0 | T28: 0 | U28: B2B2C
A29: SocialTalk | B29: Seed | C29: Influencer Marketing | D29: Portugal | E29: 44797 | F29: 831600 | G29: 831600 | H29: 7 | I29: 2 - 10 | J29: 2021 | K29: https://socialtalk.io | N29: =G29/F29 -> 1 | P29: 1 | Q29: 0 | R29: 1 | S29: 0 | T29: 0 | U29: B2B
A30: DocDigitizer | B30: Seed | C30: Cognitive AI, SaaS | D30: Portugal | E30: 44454 | F30: 1285200 | G30: 864000 | H30: 15 | I30: 11 - 50 | J30: 2017 | K30: https://www.docdigitizer.com/ | N30: =G30/F30 -> 0.67226891 | O30: 2300000 | P30: 1 | Q30: 0 | R30: 0 | S30: 1 | T30: 2 | U30: B2B
A31: Polkastarter | B31: Seed | C31: Blockchain, DeFi, Crowdfunding | D31: Portugal | E31: 44091 | F31: 875000 | G31: 875000 | H31: 18 | I31: 11 - 50 | J31: 2020 | K31: https://pols.xyz/ | N31: =G31/F31 -> 1 | P31: 0 | Q31: 0 | R31: 0 | S31: 0 | T31: 0 | U31: Unknown
A32: Noodle | B32: Seed | C32: Banking, Credit | D32: Brasil | E32: 45558 | F32: 3960000 | G32: 900000 | H32: 11 | I32: 11 - 50 | J32: 2020 | K32: https://www.noodle.cx/ | N32: =G32/F32 -> 0.22727273 | P32: 1 | Q32: 1 | R32: 0 | S32: 0 | T32: 2 | U32: B2B
A33: Codavel | B33: Seed | C33: App Performance, CDN | D33: Portugal | E33: 44470 | F33: 3132000 | G33: 972000 | H33: 5 | I33: 2 - 10 | J33: 2018 | K33: https://www.codavel.com/ | N33: =G33/F33 -> 0.31034483 | P33: 1 | Q33: 1 | R33: 2 | S33: 0 | T33: 2 | U33: B2C
A34: Konsi | B34: Seed | C34: FinTech, Payroll Loans | D34: Brasil | E34: 45467 | F34: 1611770 | G34: 1000000 | H34: 178 | I34: 101 - 250 | J34: 2021 | K34: https://www.konsi.com.br/ | N34: =G34/F34 -> 0.62043592 | P34: 0 | Q34: 0 | R34: 0 | S34: 2 | T34: 5 | U34: B2B2C
A35: Beegol | B35: Venture | C35: AI, Telecom | D35: Brasil | E35: 45632 | F35: 5600000 | G35: 1000000 | H35: 60 | I35: 51 - 100 | J35: 2019 | K35: https://www.beegol.com/ | N35: =G35/F35 -> 0.17857143 | P35: 0 | Q35: 1 | R35: 1 | S35: 0 | T35: 0 | U35: Unknown
A36: Culttivo | B36: Series A | C36: AgTech, Coffee Credit | D36: Brasil | E36: 45981 | F36: 16547191 | G36: 1000000 | H36: 68 | I36: 51 - 100 | J36: 2020 | K36: http://www.culttivo.com | N36: =G36/F36 -> 0.060433218 | P36: 0 | Q36: 0 | R36: 0 | S36: 0 | T36: 3 | U36: B2B
A37: Fasqon | B37: Seed | C37: FinTech, Neobank, Web3 | D37: Portugal | E37: 45352 | F37: 1300000 | G37: 1000000 | H37: 9 | I37: 2 - 10 | J37: 2023 | K37: https://fasqon.com/ | N37: =G37/F37 -> 0.76923077 | P37: 0 | Q37: 0 | R37: 0 | S37: 0 | T37: 0 | U37: B2B2C
A38: Albato | B38: Seed | C38: No-code, Automation, SaaS | D38: Portugal | E38: 44197 | F38: 1000000 | G38: 1000000 | H38: 43 | I38: 11 - 50 | J38: 2019 | K38: https://albato.com/ | N38: =G38/F38 -> 1 | P38: 1 | Q38: 1 | R38: 1 | S38: 1 | T38: 5 | U38: B2B
A39: Codavel (2) | B39: Seed | C39: Video CDN, Application Perf | D39: Portugal | E39: 44501 | F39: 3298430 | G39: 1043455 | H39: 5 | I39: 2 - 10 | J39: 2018 | K39: https://www.codavel.com/ | N39: =G39/F39 -> 0.31634899 | P39: 1 | Q39: 1 | R39: 2 | S39: 0 | T39: 2 | U39: B2C
A40: Manie | B40: Seed | C40: Energy Mgmt, Consulting | D40: Portugal | E40: 45770 | F40: 1080000 | G40: 1080000 | H40: 26 | I40: 11 - 50 | J40: 2024 | K40: https://manie.pt/ | N40: =G40/F40 -> 1 | P40: 0 | Q40: 0 | R40: 0 | S40: 0 | T40: 0 | U40: Unknown
A41: Anybrain | B41: Venture | C41: AI, Data Processing | D41: Portugal | E41: 43920 | F41: 1080000 | G41: 1080000 | H41: 19 | I41: 11 - 50 | J41: 2015 | K41: https://anybrain.gg/ | N41: =G41/F41 -> 1 | P41: 1 | Q41: 0 | R41: 3 | S41: 0 | T41: 0 | U41: B2B
A42: Processware | B42: Seed | C42: IT Software | D42: Portugal | E42: 41844 | F42: 1080000 | G42: 1080000 | H42: 36 | I42: 11 - 50 | J42: 2009 | K42: https://www.processwaregroup.com/ | N42: =G42/F42 -> 1 | P42: 0 | Q42: 0 | R42: 1 | S42: 0 | T42: 1 | U42: B2B
... A48: Coreflux | B48: Seed | C48: IoT Platform, Data Mgmt | D48: Portugal | E48: 45689 | F48: 1296000 | G48: 1296000 | H48: 12 | I48: 11 - 50 | J48: 2022 | K48: https://www.coreflux.org/ | N48: =G48/F48 -> 1 | P48: 2 | Q48: 2 | R48: 2 | S48: 0 | T48: 1 | U48: B2B
A49: Flecto | B49: Venture | C49: Rental Platform, Circular Econ | D49: Portugal | E49: 44734 | F49: 1512000 | G49: 1296000 | H49: 22 | I49: 11 - 50 | J49: 2016 | K49: https://flecto.io/ | N49: =G49/F49 -> 0.85714286 | O49: 5000000 | P49: 0 | Q49: 1 | R49: 2 | S49: 2 | T49: 4 | U49: B2B
A50: Captei | B50: Seed | C50: PropTech, BI | D50: Brasil | E50: 44701 | F50: 1431000 | G50: 1350000 | H50: 40 | I50: 11 - 50 | J50: 2019 | K50: https://captei.com.br/ | N50: =G50/F50 -> 0.94339623 | P50: 0 | Q50: 1 | R50: 1 | S50: 0 | T50: 3 | U50: B2B
A51: EqSeed | B51: Seed | C51: Equity Crowdfunding | D51: Brasil | E51: 45839 | F51: 4050000 | G51: 1350000 | H51: 32 | I51: 11 - 50 | J51: 2014 | K51: https://eqseed.com/ | N51: =G51/F51 -> 0.33333333 | O51: 234000 | P51: 1 | Q51: 0 | R51: 0 | S51: 3 | T51: 4 | U51: B2B
A52: OurSupport | B52: Series A | C52: IT Support, Platform | D52: Portugal | E52: 45747 | F52: 2219400 | G52: 1404000 | H52: 60 | I52: 51 - 100 | J52: 2018 | K52: oursupport.co | N52: =G52/F52 -> 0.63260341 | P52: 0 | Q52: 0 | R52: 2 | S52: 0 | T52: 0 | U52: B2B2C
A53: Meight | B53: Venture | C53: Eco-driving, Software | D53: Portugal | E53: 43704 | F53: 1512000 | G53: 1512000 | H53: 32 | I53: 11 - 50 | J53: 2018 | K53: https://www.meight.com/ | N53: =G53/F53 -> 1 | P53: 2 | Q53: 0 | R53: 2 | S53: 0 | T53: 1 | U53: B2B
A54: Zaask | B54: Seed | C54: Local Marketplace | D54: Portugal | E54: 42005 | F54: 2311200 | G54: 1512000 | H54: 37 | I54: 11 - 50 | J54: 2012 | K54: https://www.zaask.com | N54: =G54/F54 -> 0.65420561 | P54: 0 | Q54: 1 | R54: 0 | S54: 0 | T54: 0 | U54: B2B2C
A55: Meight | B55: Venture | C55: Logistics, ML | D55: Portugal | E55: 45643 | F55: 1512000 | G55: 1512000 | H55: 32 | I55: 11 - 50 | J55: 2018 | K55: https://www.meight.com/ | N55: =G55/F55 -> 1 | P55: 2 | Q55: 0 | R55: 2 | S55: 0 | T55: 1 | U55: B2B
A56: DeepNeuronic | B56: Seed | C56: ML, Consulting, IT | D56: Portugal | E56: 44887 | F56: 1620000 | G56: 1620000 | H56: 20 | I56: 11 - 50 | J56: 2021 | K56: https://www.deepneuronic.com | N56: =G56/F56 -> 1 | P56: 2 | Q56: 0 | R56: 1 | S56: 0 | T56: 0 | U56: B2B
A57: Salvy | B57: Seed | C57: Telecom, SaaS | D57: Brasil | E57: 45425 | F57: 3300000 | G57: 1800000 | H57: 41 | I57: 11 - 50 | J57: 2022 | K57: https://salvy.com.br/ | N57: =G57/F57 -> 0.54545455 | P57: 2 | Q57: 1 | R57: 2 | S57: 0 | T57: 3 | U57: B2B
A58: Nuvia | B58: Seed | C58: Sales AI | D58: Brasil | E58: 45769 | F58: 1800000 | G58: 1800000 | H58: 26 | I58: 11 - 50 | J58: 2025 | K58: https://www.nuvia.co/ | N58: =G58/F58 -> 1 | P58: 3 | Q58: 1 | R58: 3 | S58: 0 | T58: 2 | U58: B2B
A59: Wegho | B59: Seed | C59: Home Services, Digital | D59: Portugal | E59: 43411 | F59: 1836000 | G59: 1836000 | H59: 51 | I59: 51 - 100 | J59: 2017 | K59: https://www.wegho.com/ | N59: =G59/F59 -> 1 | P59: 0 | Q59: 1 | R59: 4 | S59: 2 | T59: 4 | U59: B2C
A60: PluggableAI | B60: Seed | C60: Fan Engagement, AI | D60: Portugal | E60: 45552 | F60: 1998001 | G60: 1890000 | H60: 12 | I60: 11 - 50 | J60: 2022 | K60: https://www.fanofthematch.ai/ | N60: =G60/F60 -> 0.94594547 | P60: 1 | Q60: 0 | R60: 2 | S60: 0 | T60: 0 | U60: Unknown
A61: LUGGit | B61: Seed | C61: Travel Tech, Logistics | D61: Portugal | E61: 45251 | F61: 2376000 | G61: 1944000 | H61: 28 | I61: 11 - 50 | J61: 2019 | K61: https://luggit.app/ | N61: =G61/F61 -> 0.81818182 | O61: 2000000 | P61: 1 | Q61: 0 | R61: 1 | S61: 0 | T61: 2 | U61: B2C
A62: UbiRider | B62: Seed | C62: Fintech, SaaS | D62: Portugal | E62: 45355 | F62: 1950000 | G62: 1950000 | H62: 23 | I62: 11 - 50 | J62: 2018 | K62: https://ubirider.com/ | N62: =G62/F62 -> 1 | P62: 1 | Q62: 0 | R62: 4 | S62: 0 | T62: 0 | U62: B2B2C
A63: Arado | B63: Series B | C63: AgTech, Supply Chain | D63: Brasil | E63: 45625 | F63: 21370375 | G63: 2000000 | H63: 120 | I63: 101 - 250 | J63: 2021 | K63: http://sobre.arado.com.br | N63: =G63/F63 -> 0.093587501 | P63: 0 | Q63: 0 | R63: 0 | S63: 0 | T63: 1 | U63: B2C
A64: Glartek | B64: Venture | C64: AR, Manufacturing | D64: Portugal | E64: 45841 | F64: 3780000 | G64: 2160000 | H64: 29 | I64: 11 - 50 | J64: 2017 | K64: https://glartek.com/ | N64: =G64/F64 -> 0.57142857 | P64: 2 | Q64: 0 | R64: 0 | S64: 1 | T64: 2 | U64: B2B
A65: BM2Solar | B65: Series A | C65: Solar Energy | D65: Portugal | E65: 45841 | F65: 2970000 | G65: 2160000 | H65: 8 | I65: 11 - 50 | J65: 2023 | K65: https://www.bm2solar.com/ | N65: =G65/F65 -> 0.72727273 | P65: 0 | Q65: 1 | R65: 0 | S65: 0 | T65: 0 | U65: B2B
A66: Comudel | B66: Seed | C66: AI, Fin. Services | D66: Portugal | E66: 45748 | F66: 3780000 | G66: 2160000 | H66: 19 | I66: 11 - 50 | J66: 2022 | K66: https://comudel.com/ | N66: =G66/F66 -> 0.57142857 | P66: 0 | Q66: 1 | R66: 0 | S66: 0 | T66: 0 | U66: B2B
A67: FULLVENUE | B67: Seed | C67: AI Marketing, AdTech | D67: Portugal | E67: 45300 | F67: 2160000 | G67: 2160000 | H67: 22 | I67: 11 - 50 | J67: 2020 | K67: https://www.fullvenue.ai/ | N67: =G67/F67 -> 1 | P67: 1 | Q67: 0 | R67: 0 | S67: 1 | T67: 1 | U67: B2B2C
A68: Sqill | B68: Seed | C68: Video App, Sports Marketing | D68: Portugal | E68: 45495 | F68: 2268000 | G68: 2160000 | H68: 22 | I68: 11 - 50 | J68: 2021 | K68: https://sqill.so/ | N68: =G68/F68 -> 0.95238095 | P68: 0 | Q68: 1 | R68: 0 | S68: 0 | T68: 0 | U68: B2B2C
A69: Landing.Jobs | B69: Seed | C69: HR Tech, Recruiting | D69: Portugal | E69: 43895 | F69: 2970000 | G69: 2160000 | H69: 44 | I69: 11 - 50 | J69: 2013 | K69: https://landing.jobs/ | N69: =G69/F69 -> 0.72727273 | O69: 2900000 | P69: 1 | Q69: 0 | R69: 2 | S69: 3 | T69: 7 | U69: B2B
A70: Biometrid | B70: Series A | C70: Biometrics, IT Services | D70: Portugal | E70: 43983 | F70: 2200000 | G70: 2200000 | H70: 28 | I70: 11 - 50 | J70: 2015 | K70: www.biometrid.com | N70: =G70/F70 -> 1 | P70: 0 | Q70: 1 | R70: 1 | S70: 1 | T70: 0 | U70: B2B
A71: e-Schooling | B71: Venture | C71: EdTech, Apps | D71: Portugal | E71: 43466 | F71: 2200000 | G71: 2200000 | H71: 54 | I71: 11 - 50 | J71: 2007 | K71: http://www.e-schooling.com | N71: =G71/F71 -> 1 | P71: 0 | Q71: 0 | R71: 0 | S71: 1 | T71: 2 | U71: B2B
A72: Tecnofit | B72: Seed | C72: Wellness, SaaS | D72: Brasil | E72: 44456 | F72: 2772000 | G72: 2340000 | H72: 151 | I72: 101 - 250 | J72: 2016 | K72: https://www.tecnofit.com.br/ | N72: =G72/F72 -> 0.84415584 | O72: 12300000 | P72: 0 | Q72: 3 | R72: 4 | S72: 2 | T72: 6 | U72: B2B2C
A73: Hoopers | B73: Seed | C73: Sports Tech, Communities | D73: Portugal | E73: 45604 | F73: 2787278 | G73: 2340000 | H73: 23 | I73: 11 - 50 | J73: 2020 | K73: https://hoopers.club/ | N73: =G73/F73 -> 0.83952874 | P73: 1 | Q73: 1 | R73: 3 | S73: 0 | T73: 0 | U73: B2B2C
A74: STAGE | B74: Seed | C74: Music, Internet | D74: Portugal | E74: 45457 | F74: 2400000 | G74: 2400000 | H74: 4 | I74: 2 - 10 | J74: 2021 | K74: https://www.stage.community/ | N74: =G74/F74 -> 1 | P74: 1 | Q74: 1 | R74: 2 | S74: 0 | T74: 0 | U74: B2B2C
A75: Aravita | B75: Seed | C75: AI, AgTech | D75: Brasil | E75: 45015 | F75: 2500000 | G75: 2500000 | H75: 17 | I75: 11 - 50 | J75: 2022 | K75: https://www.aravita.com/ | N75: =G75/F75 -> 1 | O75: 1000000 | P75: 1 | Q75: 1 | R75: 0 | S75: 0 | T75: 1 | U75: B2B
A76: Visio.ai | B76: Seed | C76: AI, Comp. Vision | D76: Brasil | E76: 45363 | F76: 2500000 | G76: 2500000 | H76: 68 | I76: 51 - 100 | J76: 2021 | K76: https://www.visio.ai/ | N76: =G76/F76 -> 1 | P76: 1 | Q76: 1 | R76: 0 | S76: 0 | T76: 2 | U76: B2B
A77: 180 Seguros | B77: Venture | C77: InsurTech | D77: Brasil | E77: 45953 | F77: 51118155 | G77: 2500000 | H77: 118 | I77: 101 - 250 | J77: 2020 | K77: https://180s.com.br | N77: =G77/F77 -> 0.048906303 | O77: 68000000 | P77: 0 | Q77: 2 | R77: 3 | S77: 0 | T77: 2 | U77: B2B2C
A78: Solides | B78: Venture | C78: HR Tech, People Analytics | D78: Brasil | E78: 45576 | F78: 100440000 | G78: 2520000 | H78: 1109 | I78: 1000 - 5000 | J78: 2010 | K78: https://solides.com.br/ | N78: =G78/F78 -> 0.025089606 | O78: 91000000 | P78: 2 | Q78: 1 | R78: 10 | S78: 3 | T78: 5 | U78: B2B
A79: HiJiffy | B79: Venture | C79: Hospitality Tech | D79: Portugal | E79: 45098 | F79: 5823441 | G79: 2700000 | H79: 74 | I79: 51 - 100 | J79: 2016 | K79: https://www.hijiffy.com/ | N79: =G79/F79 -> 0.4636434 | O79: 3000000 | P79: 1 | Q79: 0 | R79: 3 | S79: 0 | T79: 2 | U79: B2B
A80: Cargofive | B80: Seed | C80: Logistics, IT | D80: Portugal | E80: 45377 | F80: 4803671 | G80: 2700000 | H80: 41 | I80: 11 - 50 | J80: 2018 | K80: https://cargofive.com/ | N80: =G80/F80 -> 0.56207013 | P80: 1 | Q80: 1 | R80: 0 | S80: 0 | T80: 1 | U80: B2B
A81: Nortech AI | B81: Seed | C81: Industrial IoT, Consulting | D81: Portugal | E81: 45222 | F81: 2700000 | G81: 2700000 | H81: 22 | I81: 11 - 50 | J81: 2021 | K81: https://www.nortech.a | N81: =G81/F81 -> 1 | P81: 0 | Q81: 0 | R81: 0 | S81: 0 | T81: 0 | U81: Unknown
A82: Sound Particles | B82: Seed | C82: Audio Software, 3D | D82: Portugal | E82: 44712 | F82: 3132000 | G82: 2700000 | H82: 18 | I82: 11 - 50 | J82: 2016 | K82: https://www.soundparticles.com/ | N82: =G82/F82 -> 0.86206897 | P82: 1 | Q82: 1 | R82: 3 | S82: 0 | T82: 2 | U82: B2B2C
A83: Voa Health | B83: Seed | C83: AI, HealthTech | D83: Brasil | E83: 45740 | F83: 3200000 | G83: 3000000 | H83: 27 | I83: 11 - 50 | J83: 2023 | K83: https://voa.health | N83: =G83/F83 -> 0.9375 | P83: 0 | Q83: 0 | R83: 0 | S83: 0 | T83: 1 | U83: B2B
A84: Agrolend | B84: Series C | C84: AgFintech, Credit | D84: Brasil | E84: 45806 | F84: 162578377 | G84: 3000000 | H84: 71 | I84: 51 - 100 | J84: 2020 | K84: https://agrolend.agr.br/ | N84: =G84/F84 -> 0.018452638 | O84: 1500000 | P84: 2 | Q84: 1 | R84: 1 | S84: 0 | T84: 0 | U84: B2B
A85: Cumbuca | B85: Seed | C85: FinTech, Payments | D85: Brasil | E85: 45162 | F85: 3125000 | G85: 3000000 | H85: 50 | I85: 11 - 50 | J85: 2021 | K85: https://www.cumbuca.com/ | N85: =G85/F85 -> 0.96 | O85: 650000 | P85: 0 | Q85: 2 | R85: 0 | S85: 5 | T85: 5 | U85: B2B
A86: pleez | B86: Venture | C86: FoodTech, Data | D86: Portugal | E86: 45602 | F86: 6970906 | G86: 3000000 | H86: 28 | I86: 11 - 50 | J86: 2020 | K86: http://www.trypleez.com | N86: =G86/F86 -> 0.43036013 | P86: 1 | Q86: 0 | R86: 0 | S86: 1 | T86: 0 | U86: B2B2C
A87: Morada.ai | B87: Series A | C87: AI, Real Estate | D87: Brasil | E87: 46000 | F87: 5184000 | G87: 3060000 | H87: 83 | I87: 51 - 100 | J87: 2021 | K87: https://morada.ai/ | N87: =G87/F87 -> 0.59027778 | P87: 1 | Q87: 1 | R87: 4 | S87: 1 | T87: 2 | U87: B2B
A88: Cromai | B88: Series A | C88: AgTech, AI/ML | D88: Brasil | E88: 45349 | F88: 6660000 | G88: 3060000 | H88: 50 | I88: 11 - 50 | J88: 2017 | K88: https://www.cromai.com/ | N88: =G88/F88 -> 0.45945946 | O88: 13600000 | P88: 0 | Q88: 0 | R88: 1 | S88: 1 | T88: 1 | U88: B2B
A89: Bipa | B89: Seed | C89: Bitcoin, Lightning | D89: Brasil | E89: 45631 | F89: 22053722 | G89: 3060000 | H89: 57 | I89: 51 - 100 | J89: 2020 | K89: https://bipa.app/ | N89: =G89/F89 -> 0.13875209 | P89: 0 | Q89: 2 | R89: 1 | S89: 0 | T89: 1 | U89: B2C
A90: GoParity | B90: Venture | C90: Fintech, CleanTech | D90: Portugal | E90: 45779 | F90: 8444063 | G90: 3132000 | H90: 43 | I90: 11 - 50 | J90: 2017 | K90: http://www.goparity.com | N90: =G90/F90 -> 0.37091149 | P90: 1 | Q90: 0 | R90: 0 | S90: 1 | T90: 1 | U90: B2B2C
A91: proGrow | B91: Seed | C91: IoT, SaaS, Industrial | D91: Portugal | E91: 44806 | F91: 4968000 | G91: 3132000 | H91: 30 | I91: 11 - 50 | J91: 2014 | K91: https://www.progrow.ai/ | N91: =G91/F91 -> 0.63043478 | P91: 0 | Q91: 3 | R91: 7 | S91: 1 | T91: 2 | U91: B2B
A92: Barkyn | B92: Series A | C92: Pet Care, E-Comm | D92: Portugal | E92: 44314 | F92: 11664000 | G92: 3240000 | H92: 48 | I92: 11 - 50 | J92: 2017 | K92: https://barkyn.com/ | N92: =G92/F92 -> 0.27777778 | O92: 6500000 | P92: 0 | Q92: 0 | R92: 1 | S92: 0 | T92: 2 | U92: B2C
A93: LoopOS | B93: Seed | C93: ERP, SaaS, Circular | D93: Portugal | E93: 45705 | F93: 3240000 | G93: 3240000 | H93: 35 | I93: 11 - 50 | J93: 2022 | K93: https://www.getloopos.com/ | N93: =G93/F93 -> 1 | P93: 0 | Q93: 1 | R93: 2 | S93: 0 | T93: 0 | U93: B2B
A94: WEEZIE | B94: Seed | C94: Fiber Network Software | D94: Portugal | E94: 45328 | F94: 3807000 | G94: 3240000 | H94: 23 | I94: 11 - 50 | J94: 2018 | K94: https://weezie.io | N94: =G94/F94 -> 0.85106383 | P94: 0 | Q94: 0 | R94: 0 | S94: 0 | T94: 0 | U94: B2B
A95: Colmeia | B95: Venture | C95: SaaS, Telecom | D95: Brasil | E95: 45985 | F95: 8100000 | G95: 3240000 | H95: 117 | I95: 101 - 250 | J95: 2019 | K95: https://colmeia.cx/ | N95: =G95/F95 -> 0.4 | P95: 0 | Q95: 1 | R95: 3 | S95: 0 | T95: 3 | U95: B2B
A96: Virtuleap | B96: Seed | C96: Health Tech, VR, Neuroscience | D96: Portugal | E96: 44927 | F96: 4904500 | G96: 3300000 | H96: 30 | I96: 11 - 50 | J96: 2018 | K96: http://www.virtuleap.com | N96: =G96/F96 -> 0.67285146 | O96: 3606000 | P96: 1 | Q96: 0 | R96: 0 | S96: 1 | T96: 1 | U96: B2B
A97: Lumx | B97: Seed | C97: Web3, Stablecoins | D97: Brasil | E97: 45945 | F97: 3400000 | G97: 3400000 | H97: 45 | I97: 11 - 50 | J97: https://lumx.io/ | K97: https://lumx.io/ | N97: =G97/F97 -> 1 | P97: 0 | Q97: 1 | R97: 1 | S97: 0 | T97: 3 | U97: B2B
A98: Portão 3 | B98: Seed | C98: Travel Mgmt | D98: Brasil | E98: 44944 | F98: 3700000 | G98: 3600000 | H98: 3 | I98: 2 - 10 | J98: 2020 | K98: https://portao3.com.br | N98: =G98/F98 -> 0.97297297 | O98: #N/A | P98: #N/A | Q98: #N/A | R98: #N/A | S98: #N/A | T98: #N/A | U98: #N/A
A99: Exato Digital | B99: Series A | C99: Background Check | D99: Brasil | E99: 45931 | F99: 7598489 | G99: 3600000 | H99: 51 | I99: 51 - 100 | J99: 2018 | K99: https://exato.digital/ | N99: =G99/F99 -> 0.47377841 | P99: 1 | Q99: 0 | R99: 1 | S99: 2 | T99: 4 | U99: B2B
A100: Hole19 | B100: Seed | C100: Golf App, Marketplace | D100: Portugal | E100: 42956 | F100: 3742200 | G100: 3742200 | H100: 52 | I100: 51 - 100 | J100: 2011 | K100: https://www.hole19golf.com/ | N100: =G100/F100 -> 1 | O100: 4000000 | P100: 1 | Q100: 0 | R100: 2 | S100: 2 | T100: 2 | U100: B2C
A101: Spotlite | B101: Seed | C101: Remote Sensing | D101: Portugal | E101: 45994 | F101: 5400000 | G101: 3780000 | H101: 29 | I101: 11 - 50 | J101: 2021 | K101: https://spotlitedata.com/ | N101: =G101/F101 -> 0.7 | O101: 1200000 | P101: 2 | Q101: 0 | R101: 0 | S101: 0 | T101: 0 | U101: B2B
A102: DreamShaper | B102: Venture | C102: EdTech, E-Learning | D102: Portugal | E102: 43775 | F102: 3780000 | G102: 3780000 | H102: 72 | I102: 51 - 100 | J102: 2014 | K102: https://www.dreamshaper.com/ | N102: =G102/F102 -> 1 | P102: 0 | Q102: 1 | R102: 2 | S102: 1 | T102: 0 | U102: B2B
A103: Liti | B103: Seed | C103: Health Care | D103: Brasil | E103: 44874 | F103: 6000000 | G103: 3780000 | H103: 76 | I103: 51 - 100 | J103: 2021 | K103: https://liti.com.br/pt | N103: =G103/F103 -> 0.63 | P103: 0 | Q103: 1 | R103: 1 | S103: 2 | T103: 2 | U103: B2C
A104: GuestCentric | B104: Venture | C104: Hotel Ecommerce, Travel | D104: Portugal | E104: 40008 | F104: 5250000 | G104: 4000000 | H104: 53 | I104: 51 - 100 | J104: 2006 | K104: https://guestcentric.com/ | N104: =G104/F104 -> 0.76190476 | O104: 4500000 | P104: 0 | Q104: 0 | R104: 2 | S104: 0 | T104: 2 | U104: B2B
A105: Zharta | B105: Seed | C105: NFT Lending, FinTech | D105: Portugal | E105: 44762 | F105: 4300000 | G105: 4300000 | H105: 11 | I105: 11 - 50 | J105: 2021 | K105: https://www.zharta.io/ | N105: =G105/F105 -> 1 | P105: 0 | Q105: 1 | R105: 1 | S105: 1 | T105: 1 | U105: B2B2C
A106: ETHIACK | B106: Seed | C106: AI, Cyber Security | D106: Portugal | E106: 45636 | F106: 4404240 | G106: 4320000 | H106: 52 | I106: 51 - 100 | J106: 2022 | K106: https://ethiack.com/ | N106: =G106/F106 -> 0.98087298 | P106: 1 | Q106: 0 | R106: 1 | S106: 0 | T106: 2 | U106: B2B
A107: Accountfy | B107: Series A | C107: SaaS, Fin. Mgmt | D107: Brasil | E107: 44364 | F107: 11000000 | G107: 4500000 | H107: 312 | I107: 251 - 500 | J107: 2017 | K107: https://www.accountfy.com/ | N107: =G107/F107 -> 0.40909091 | P107: 1 | Q107: 0 | R107: 1 | S107: 1 | T107: 4 | U107: B2B
...

Sheet Base Final
A1: Empresa | B1: País | C1: Site | D1: Fundação | E1: Setor | F1: Tipo de Financiamento | G1: Faixa de HC | H1: Funcionários | I1: Idade (anos) | J1: Total Captado (USD) | K1: Último Aporte | L1: Data Últ. Finan. | M1: Captação per HC | N1: Último Aporte per HC | O1: Intensidade Histórica (Total Captado/Anos de fundação) | P1: Momentum (%ult aporte/total captado) | Q1: N Tecnologias | R1: Score Deeptech | S1: Score Cloud Native | T1: Score DevTools | U1: Score Analytics | V1: Score Growth Stack | W1: Modelo de NegÃ³cio
A2: GFoundry | B2: Portugal | C2: http://gfoundry.com | D2: 2014 | E2: HR Tech, Gamification | F2: Seed | G2: =VLOOKUP(A2,'Dataset '!A:I,9,0) -> 2 - 10 | H2: 4 | I2: 11 | J2: 324000 | K2: 324000 | L2: =VLOOKUP($A2,'Dataset '!$A:$I,5,0) -> 41820 | M2: =J2/H2 -> 81000 | N2: =K2/H2 -> 81000 | O2: =J2/I2 -> 29454.545 | P2: =K2/J2 -> 1 | Q2: 17 | R2: 1 | S2: 0 | T2: 1 | U2: 0 | V2: 1 | W2: B2B
A3: BioMimetx | B3: Portugal | C3: https://www.biomimetx.com/ | D3: 2013 | E3: Biotech, Biofuel | F3: Seed | G3: =VLOOKUP(A3,'Dataset '!A:I,9,0) -> 2 - 10 | H3: 6 | I3: 12 | J3: 3996000 | K3: 540000 | L3: =VLOOKUP($A3,'Dataset '!$A:$I,5,0) -> 44918 | M3: =J3/H3 -> 666000 | N3: =K3/H3 -> 90000 | O3: =J3/I3 -> 333000 | P3: =K3/J3 -> 0.13513514 | Q3: 10 | R3: 1 | S3: 0 | T3: 0 | U3: 0 | V3: 0 | W3: B2B
A4: Bandora | B4: Portugal | C4: http://www.bandorasystems.com | D4: 2017 | E4: AI, Smart Building | F4: Venture | G4: =VLOOKUP($A4,'Dataset '!$A:$I,9,0) -> 11 - 50 | H4: 31 | I4: 8 | J4: 2306214 | K4: 108000 | L4: =VLOOKUP($A4,'Dataset '!$A:$I,5,0) -> 45832 | M4: =J4/H4 -> 74394 | N4: =K4/H4 -> 3483.871 | O4: =J4/I4 -> 288276.75 | P4: =K4/J4 -> 0.046829999 | Q4: 12 | R4: 1 | S4: 0 | T4: 1 | U4: 0 | V4: 2 | W4: B2B
A5: Merytu | B5: Portugal | C5: https://merytu.com/ | D5: 2019 | E5: Employment, Mobile Apps | F5: Seed | G5: =VLOOKUP(A5,'Dataset '!A:I,9,0) -> 11 - 50 | H5: 34 | I5: 6 | J5: 216000 | K5: 216000 | L5: =VLOOKUP($A5,'Dataset '!$A:$I,5,0) -> 44294 | M5: =J5/H5 -> 6352.9412 | N5: =K5/H5 -> 6352.9412 | O5: =J5/I5 -> 36000 | P5: =K5/J5 -> 1 | Q5: 17 | R5: 0 | S5: 0 | T5: 0 | U5: 1 | V5: 1 | W5: B2C
A6: MagniFinance | B6: Portugal | C6: http://www.magnifinance.com | D6: 2015 | E6: Fintech, Cashflow Mgmt | F6: Seed | G6: =VLOOKUP(A6,'Dataset '!A:I,9,0) -> 11 - 50 | H6: 5 | I6: 10 | J6: 216000 | K6: 216000 | L6: =VLOOKUP($A6,'Dataset '!$A:$I,5,0) -> 42064 | M6: =J6/H6 -> 43200 | N6: =K6/H6 -> 43200 | O6: =J6/I6 -> 21600 | P6: =K6/J6 -> 1 | Q6: 27 | R6: 0 | S6: 0 | T6: 0 | U6: 1 | V6: 6 | W6: B2B
A7: PLUX biosignals | B7: Portugal | C7: http://www.pluxbiosignals.com | D7: 2007 | E7: Medical Device, Wireless | F7: Seed | G7: =VLOOKUP(A7,'Dataset '!A:I,9,0) -> 11 - 50 | H7: 35 | I7: 18 | J7: 788400 | K7: 248400 | L7: =VLOOKUP($A7,'Dataset '!$A:$I,5,0) -> 41548 | M7: =J7/H7 -> 22525.714 | N7: =K7/H7 -> 7097.1429 | O7: =J7/I7 -> 43800 | P7: =K7/J7 -> 0.31506849 | Q7: 45 | R7: 0 | S7: 0 | T7: 1 | U7: 1 | V7: 4 | W7: B2C
A8: Dig. Manager Guru | B8: Portugal | C8: https://digitalmanager.guru | D8: 2017 | E8: Sales Mgmt, Retail Tech | F8: Seed | G8: =VLOOKUP(A8,'Dataset '!A:I,9,0) -> 11 - 50 | H8: 46 | I8: 8 | J8: 324000 | K8: 324000 | L8: =VLOOKUP($A8,'Dataset '!$A:$I,5,0) -> 43524 | M8: =J8/H8 -> 7043.4783 | N8: =K8/H8 -> 7043.4783 | O8: =J8/I8 -> 40500 | P8: =K8/J8 -> 1 | Q8: 23 | R8: 0 | S8: 0 | T8: 0 | U8: 1 | V8: 3 | W8: B2B2C
A9: Infinite Foundry | B9: Portugal | C9: https://www.infinitefoundry.com/ | D9: 2017 | E9: 3D, Industrial VR | F9: Seed | G9: =VLOOKUP(A9,'Dataset '!A:I,9,0) -> 11 - 50 | H9: 35 | I9: 8 | J9: 540000 | K9: 540000 | L9: =VLOOKUP($A9,'Dataset '!$A:$I,5,0) -> 43451 | M9: =J9/H9 -> 15428.571 | N9: =K9/H9 -> 15428.571 | O9: =J9/I9 -> 67500 | P9: =K9/J9 -> 1 | Q9: 17 | R9: 1 | S9: 1 | T9: 0 | U9: 0 | V9: 0 | W9: B2B
A10: beamian | B10: Portugal | C10: http://beamian.com | D10: 2019 | E10: Event Tech, IoT, NFC | F10: Seed | G10: =VLOOKUP(A10,'Dataset '!A:I,9,0) -> 2 - 10 | H10: 7 | I10: 6 | J10: 864000 | K10: 648000 | L10: =VLOOKUP($A10,'Dataset '!$A:$I,5,0) -> 43646 | M10: =J10/H10 -> 123428.57 | N10: =K10/H10 -> 92571.429 | O10: =J10/I10 -> 144000 | P10: =K10/J10 -> 0.75 | Q10: 25 | R10: 0 | S10: 0 | T10: 1 | U10: 1 | V10: 3 | W10: B2C
A11: Bitcliq | B11: Portugal | C11: http://www.bitcliq.com | D11: 2013 | E11: Blockchain, IoT, Fishing | F11: Seed | G11: =VLOOKUP(A11,'Dataset '!A:I,9,0) -> 2 - 10 | H11: 5 | I11: 12 | J11: 648000 | K11: 648000 | L11: =VLOOKUP($A11,'Dataset '!$A:$I,5,0) -> 43504 | M11: =J11/H11 -> 129600 | N11: =K11/H11 -> 129600 | O11: =J11/I11 -> 54000 | P11: =K11/J11 -> 1 | Q11: 15 | R11: 1 | S11: 0 | T11: 1 | U11: 1 | V11: 0 | W11: B2B2C
A12: InKlusion | B12: Portugal | C12: https://inklusion.pt | D12: 2013 | E12: Software, 3D Design | F12: Seed | G12: =VLOOKUP(A12,'Dataset '!A:I,9,0) -> 2 - 10 | H12: 5 | I12: 12 | J12: 756000 | K12: 756000 | L12: =VLOOKUP($A12,'Dataset '!$A:$I,5,0) -> 44864 | M12: =J12/H12 -> 151200 | N12: =K12/H12 -> 151200 | O12: =J12/I12 -> 63000 | P12: =K12/J12 -> 1 | Q12: 13 | R12: 2 | S12: 0 | T12: 1 | U12: 0 | V12: 0 | W12: B2B2C
A13: SocialTalk | B13: Portugal | C13: https://socialtalk.io | D13: 2021 | E13: Influencer Marketing | F13: Seed | G13: =VLOOKUP(A13,'Dataset '!A:I,9,0) -> 2 - 10 | H13: 7 | I13: 4 | J13: 831600 | K13: 831600 | L13: =VLOOKUP($A13,'Dataset '!$A:$I,5,0) -> 44797 | M13: =J13/H13 -> 118800 | N13: =K13/H13 -> 118800 | O13: =J13/I13 -> 207900 | P13: =K13/J13 -> 1 | Q13: 10 | R13: 1 | S13: 0 | T13: 1 | U13: 0 | V13: 0 | W13: B2B
A14: DocDigitizer | B14: Portugal | C14: https://www.docdigitizer.com/ | D14: 2017 | E14: Cognitive AI, SaaS | F14: Seed | G14: =VLOOKUP(A14,'Dataset '!A:I,9,0) -> 11 - 50 | H14: 15 | I14: 8 | J14: 1285200 | K14: 864000 | L14: =VLOOKUP($A14,'Dataset '!$A:$I,5,0) -> 44454 | M14: =J14/H14 -> 85680 | N14: =K14/H14 -> 57600 | O14: =J14/I14 -> 160650 | P14: =K14/J14 -> 0.67226891 | Q14: 21 | R14: 1 | S14: 0 | T14: 0 | U14: 1 | V14: 2 | W14: B2B
A15: Codavel | B15: Portugal | C15: https://www.codavel.com/ | D15: 2018 | E15: App Performance, CDN | F15: Seed | G15: =VLOOKUP(A15,'Dataset '!A:I,9,0) -> 2 - 10 | H15: 5 | I15: 7 | J15: 3132000 | K15: 972000 | L15: =VLOOKUP($A15,'Dataset '!$A:$I,5,0) -> 44470 | M15: =J15/H15 -> 626400 | N15: =K15/H15 -> 194400 | O15: =J15/I15 -> 447428.57 | P15: =K15/J15 -> 0.31034483 | Q15: 17 | R15: 1 | S15: 1 | T15: 2 | U15: 0 | V15: 2 | W15: B2C
A16: Aravita | B16: Brasil | C16: https://www.aravita.com/ | D16: 2022 | E16: AI, AgTech | F16: Seed | G16: =VLOOKUP(A16,'Dataset '!A:I,9,0) -> 11 - 50 | H16: 18 | I16: 3 | J16: 2500000 | K16: 2500000 | L16: =VLOOKUP($A16,'Dataset '!$A:$I,5,0) -> 45015 | M16: =J16/H16 -> 138888.89 | N16: =K16/H16 -> 138888.89 | O16: =J16/I16 -> 833333.33 | P16: =K16/J16 -> 1 | Q16: 15 | R16: 1 | S16: 1 | T16: 0 | U16: 0 | V16: 1 | W16: B2B
... A31: GeoInovaAI | B31: Brasil | C31: https://geoinova.com.br/ | D31: 2024 | E31: AgTech, Computer Vision | F31: Seed | G31: =VLOOKUP(A31,'Dataset '!A:I,9,0) -> 2 - 10 | H31: 10 | I31: 1 | J31: 300000 | K31: 250000 | L31: =VLOOKUP($A31,'Dataset '!$A:$I,5,0) -> 45667 | M31: =J31/H31 -> 30000 | N31: =K31/H31 -> 25000 | O31: =J31/I31 -> 300000 | P31: =K31/J31 -> 0.83333333 | Q31: 29 | R31: 1 | S31: 1 | T31: 1 | U31: 2 | V31: 1 | W31: B2B
A32: Cumbuca | B32: Brasil | C32: https://www.cumbuca.com/ | D32: 2021 | E32: FinTech, Payments | F32: Seed | G32: =VLOOKUP(A32,'Dataset '!A:I,9,0) -> 11 - 50 | H32: 49 | I32: 4 | J32: 3125000 | K32: 3000000 | L32: =VLOOKUP($A32,'Dataset '!$A:$I,5,0) -> 45162 | M32: 104166.67 | N32: =K32/H32 -> 61224.49 | O32: =J32/I32 -> 781250 | P32: =K32/J32 -> 0.96 | Q32: 27 | R32: 0 | S32: 2 | T32: 0 | U32: 5 | V32: 5 | W32: B2B
A33: pleez | B33: Portugal | C33: http://www.trypleez.com | D33: 2020 | E33: FoodTech, Data | F33: Venture | G33: =VLOOKUP(A33,'Dataset '!A:I,9,0) -> 11 - 50 | H33: 27 | I33: 5 | J33: 6970906 | K33: 3000000 | L33: =VLOOKUP($A33,'Dataset '!$A:$I,5,0) -> 45602 | M33: 232363.53 | N33: =K33/H33 -> 111111.11 | O33: =J33/I33 -> 1394181.2 | P33: =K33/J33 -> 0.43036013 | Q33: 14 | R33: 1 | S33: 0 | T33: 0 | U33: 1 | V33: 0 | W33: B2B2C
A34: Virtuleap | B34: Portugal | C34: http://www.virtuleap.com | D34: 2018 | E34: Health Tech, VR, Neuroscience | F34: Seed | G34: =VLOOKUP(A34,'Dataset '!A:I,9,0) -> 11 - 50 | H34: 30 | I34: 7 | J34: 4904500 | K34: 3300000 | L34: =VLOOKUP($A34,'Dataset '!$A:$I,5,0) -> 44927 | M34: 163483.33 | N34: =K34/H34 -> 110000 | O34: =J34/I34 -> 700642.86 | P34: =K34/J34 -> 0.67285146 | Q34: 12 | R34: 1 | S34: 0 | T34: 0 | U34: 1 | V34: 1 | W34: B2B
A35: Lumx | B35: Brasil | C35: https://lumx.io/ | D35: https://lumx.io/ | E35: Web3, Stablecoins | F35: Seed | G35: =VLOOKUP(A35,'Dataset '!A:I,9,0) -> 11 - 50 | H35: 42 | J35: 3400000 | K35: 3400000 | L35: =VLOOKUP($A35,'Dataset '!$A:$I,5,0) -> 45945 | M35: 113333.33 | N35: =K35/H35 -> 80952.381 | O35: =J35/I35 -> #DIV/0! | P35: =K35/J35 -> 1 | Q35: 19 | R35: 0 | S35: 1 | T35: 1 | U35: 0 | V35: 3 | W35: B2B
A36: Ethena | B36: Portugal | C36: https://ethena.fi/ | D36: 2023 | E36: Blockchain, DeFi | F36: Venture | G36: =VLOOKUP(A36,'Dataset '!A:I,9,0) -> 11 - 50 | H36: 15 | I36: 2 | J36: 206820000 | K36: 30000000 | L36: =VLOOKUP($A36,'Dataset '!$A:$I,5,0) -> 45931 | M36: 6894000.0 | N36: =K36/H36 -> 2000000 | O36: =J36/I36 -> 103410000 | P36: =K36/J36 -> 0.14505367 | Q36: 16 | R36: 1 | S36: 3 | T36: 1 | U36: 1 | V36: 0 | W36: B2B2C
A37: Zharta | B37: Portugal | C37: https://www.zharta.io/ | D37: 2021 | E37: NFT Lending, FinTech | F37: Seed | G37: =VLOOKUP(A37,'Dataset '!A:I,9,0) -> 11 - 50 | H37: 11 | I37: 4 | J37: 4300000 | K37: 4300000 | L37: =VLOOKUP($A37,'Dataset '!$A:$I,5,0) -> 44762 | M37: 143333.33 | N37: =K37/H37 -> 390909.09 | O37: =J37/I37 -> 1075000 | P37: =K37/J37 -> 1 | Q37: 13 | R37: 0 | S37: 1 | T37: 1 | U37: 1 | V37: 1 | W37: B2B2C
A38: Ruvo | B38: Brasil | C38: https://ruvo.com/pt | D38: 2026 | E38: Crypto, Global Acc | F38: Seed | G38: =VLOOKUP(A38,'Dataset '!A:I,9,0) -> 11 - 50 | H38: 25 | I38: -1 | J38: 5100000 | K38: 4600000 | L38: =VLOOKUP($A38,'Dataset '!$A:$I,5,0) -> 46056 | M38: 170000.0 | N38: =K38/H38 -> 184000 | O38: =J38/I38 -> -5100000 | P38: =K38/J38 -> 0.90196078 | Q38: 6 | R38: 0 | S38: 1 | T38: 0 | U38: 0 | V38: 0 | W38: Unknown
A39: Pink App | B39: Brasil | C39: https://www.pinkapp.com/ | D39: 2019 | E39: Collaboration, SaaS | F39: Seed | G39: =VLOOKUP(A39,'Dataset '!A:I,9,0) -> 11 - 50 | H39: 24 | I39: 6 | J39: 735093 | K39: 400000 | L39: =VLOOKUP($A39,'Dataset '!$A:$I,5,0) -> 43831 | M39: 24503.1 | N39: =K39/H39 -> 16666.667 | O39: =J39/I39 -> 122515.5 | P39: =K39/J39 -> 0.54414884 | Q39: 10 | R39: 0 | S39: 1 | T39: 0 | U39: 2 | V39: 0 | W39: B2B
A40: Magie | B40: Brasil | C40: https://magie.com.br/ | D40: 2023 | E40: WhatsApp Banking | F40: Seed | G40: =VLOOKUP(A40,'Dataset '!A:I,9,0) -> 11 - 50 | H40: 37 | I40: 2 | J40: 10116153 | K40: 5000000 | L40: =VLOOKUP($A40,'Dataset '!$A:$I,5,0) -> 46036 | M40: 337205.1 | N40: =K40/H40 -> 135135.14 | O40: =J40/I40 -> 5058076.5 | P40: =K40/J40 -> 0.49425903 | Q40: 12 | R40: 0 | S40: 0 | T40: 0 | U40: 1 | V40: 1 | W40: B2C
A41: Mobmio | B41: Portugal | C41: https://mobmio.com/ | D41: 2023 | E41: Mobile Marketing | F41: Series A | G41: =VLOOKUP(A41,'Dataset '!A:I,9,0) -> 2 - 10 | H41: 10 | I41: 2 | J41: 500000 | K41: 500000 | L41: =VLOOKUP($A41,'Dataset '!$A:$I,5,0) -> 45311 | M41: 16666.67 | N41: =K41/H41 -> 50000 | O41: =J41/I41 -> 250000 | P41: =K41/J41 -> 1 | Q41: 10 | R41: 0 | S41: 1 | T41: 0 | U41: 0 | V41: 2 | W41: B2C
A42: AIDigitalEngine | B42: Portugal | C42: https://www.ai-digitalengine.com/ | D42: 2021 | E42: Generative AI, RPA, Software | F42: Seed | G42: =VLOOKUP(A42,'Dataset '!A:I,9,0) -> 11 - 50 | H42: 1 | I42: 4 | J42: 103000 | K42: 65000 | L42: =VLOOKUP($A42,'Dataset '!$A:$I,5,0) -> 45168 | M42: 3433.33 | N42: =K42/H42 -> 65000 | O42: =J42/I42 -> 25750 | P42: =K42/J42 -> 0.63106796 | Q42: 6 | R42: 0 | S42: 1 | T42: 0 | U42: 0 | V42: 0 | W42: Unknown
A43: Didimo | B43: Portugal | C43: https://www.didimo.co/ | D43: 2016 | E43: 3D, AI, Avatars | F43: Series A | G43: =VLOOKUP(A43,'Dataset '!A:I,9,0) -> 11 - 50 | H43: 33 | I43: 9 | J43: 16048983 | K43: 7150000 | L43: =VLOOKUP($A43,'Dataset '!$A:$I,5,0) -> 44845 | M43: 534966.1 | N43: =K43/H43 -> 216666.67 | O43: =J43/I43 -> 1783220.3 | P43: =K43/J43 -> 0.4455111 | Q43: 15 | R43: 1 | S43: 1 | T43: 1 | U43: 0 | V43: 2 | W43: B2B2C
A44: Galaxies | B44: Brasil | C44: https://www.galaxies.com.br/ | D44: 2022 | E44: Synthetic Personas, AI | F44: Seed | G44: =VLOOKUP(A44,'Dataset '!A:I,9,0) -> 11 - 50 | H44: 51 | I44: 3 | J44: 1450000 | K44: 700000 | L44: =VLOOKUP($A44,'Dataset '!$A:$I,5,0) -> 45931 | M44: 48333.33 | N44: =K44/H44 -> 13725.49 | O44: =J44/I44 -> 483333.33 | P44: =K44/J44 -> 0.48275862 | Q44: 14 | R44: 0 | S44: 1 | T44: 0 | U44: 2 | V44: 2 | W44: B2C
A45: NOMADX | B45: Portugal | C45: http://nomadx.com/ | D45: 2017 | E45: Travel, Marketplace | F45: Seed | G45: =VLOOKUP(A45,'Dataset '!A:I,9,0) -> 2 - 10 | H45: 7 | I45: 8 | J45: 1000000 | K45: 750000 | L45: =VLOOKUP($A45,'Dataset '!$A:$I,5,0) -> 43861 | M45: 33333.33 | N45: =K45/H45 -> 107142.86 | O45: =J45/I45 -> 125000 | P45: =K45/J45 -> 0.75 | Q45: 12 | R45: 0 | S45: 0 | T45: 0 | U45: 1 | V45: 1 | W45: B2C
A46: Polkastarter | B46: Portugal | C46: https://pols.xyz/ | D46: 2020 | E46: Blockchain, DeFi, Crowdfunding | F46: Seed | G46: =VLOOKUP(A46,'Dataset '!A:I,9,0) -> 11 - 50 | H46: 30 | I46: 5 | J46: 875000 | K46: 875000 | L46: =VLOOKUP($A46,'Dataset '!$A:$I,5,0) -> 44091 | M46: 29166.67 | N46: =K46/H46 -> 29166.667 | O46: =J46/I46 -> 175000 | P46: =K46/J46 -> 1 | Q46: 0 | R46: 0 | S46: 0 | T46: 0 | U46: 0 | V46: 0 | W46: Unknown
A47: Telepatia | B47: Brasil | C47: https://www.telepatia.ai/pt-br | D47: 2025 | E47: Health Tech, AI | F47: Seed | G47: =VLOOKUP(A47,'Dataset '!A:I,9,0) -> 11 - 50 | H47: 39 | I47: 0 | J47: 9000000 | K47: 9000000 | L47: =VLOOKUP($A47,'Dataset '!$A:$I,5,0) -> 45940 | M47: 300000.0 | N47: =K47/H47 -> 230769.23 | O47: =J47/I47 -> #DIV/0! | P47: =K47/J47 -> 1 | Q47: 8 | R47: 0 | S47: 0 | T47: 0 | U47: 0 | V47: 1 | W47: Unknown
... A101: Avenia | B101: Brasil | C101: https://avenia.io/ | D101: 2023 | E101: Blockchain, FX | F101: Series A | G101: =VLOOKUP(A101,'Dataset '!A:I,9,0) -> 11 - 50 | H101: 26 | I101: 2 | J101: 18900000 | K101: 16200000 | L101: =VLOOKUP($A101,'Dataset '!$A:$I,5,0) -> 46062 | M101: 630000.0 | N101: =K101/H101 -> 623076.92 | O101: =J101/I101 -> 9450000 | P101: =K101/J101 -> 0.85714286 | Q101: 11 | R101: 1 | S101: 0 | T101: 1 | U101: 0 | V101: 0 | W101: B2B
A102: Ubiwhere | B102: Portugal | C102: http://www.ubiwhere.com | D102: 2007 | E102: Smart Cities, Software | F102: Seed | G102: =VLOOKUP(A102,'Dataset '!A:I,9,0) -> 51 - 100 | H102: 57 | I102: 18 | J102: 108000 | K102: 108000 | L102: =VLOOKUP($A102,'Dataset '!$A:$I,5,0) -> 43132 | M102: =J102/H102 -> 1894.7368 | N102: =K102/H102 -> 1894.7368 | O102: =J102/I102 -> 6000 | P102: =K102/J102 -> 1 | Q102: 20 | R102: 2 | S102: 2 | T102: 1 | U102: 1 | V102: 1 | W102: B2B
A103: B-PARTS | B103: Portugal | C103: https://www.b-parts.com | D103: 2013 | E103: Automotive E-Comm | F103: Seed | G103: =VLOOKUP(A103,'Dataset '!A:I,9,0) -> 51 - 100 | H103: 70 | I103: 12 | J103: 702000 | K103: 702000 | L103: =VLOOKUP($A103,'Dataset '!$A:$I,5,0) -> 41830 | M103: =J103/H103 -> 10028.571 | N103: =K103/H103 -> 10028.571 | O103: =J103/I103 -> 58500 | P103: =K103/J103 -> 1 | Q103: 26 | R103: 0 | S103: 1 | T103: 0 | U103: 3 | V103: 4 | W103: B2C
A104: Delend | B104: Brasil | C104: https://www.delend.finance/ | D104: 2023 | E104: FinTech, SaaS | F104: Seed | G104: =VLOOKUP(A104,'Dataset '!A:I,9,0) -> 11 - 50 | H104: 18 | I104: 2 | J104: 20100000 | K104: 10000000 | L104: =VLOOKUP($A104,'Dataset '!$A:$I,5,0) -> 45379 | M104: =J104/H104 -> 1116666.7 | N104: =K104/H104 -> 555555.56 | O104: =J104/I104 -> 10050000 | P104: =K104/J104 -> 0.49751244 | Q104: 10 | R104: 1 | S104: 1 | T104: 0 | U104: 0 | V104: 0 | W104: B2B
A105: Dolado | B105: Brasil | C105: http://dolado.com.br | D105: 2020 | E105: B2B, Marketplace | F105: Series A | G105: =VLOOKUP(A105,'Dataset '!A:I,9,0) -> 51 - 100 | H105: 75 | I105: 5 | J105: 12200000 | K105: 10000000 | L105: =VLOOKUP($A105,'Dataset '!$A:$I,5,0) -> 44656 | M105: =J105/H105 -> 162666.67 | N105: =K105/H105 -> 133333.33 | O105: =J105/I105 -> 2440000 | P105: =K105/J105 -> 0.81967213 | Q105: 4 | R105: 0 | S105: 0 | T105: 0 | U105: 0 | V105: 0 | W105: B2B2C
A106: Visio.ai | B106: Brasil | C106: https://www.visio.ai/ | D106: 2021 | E106: AI, Comp. Vision | F106: Seed | G106: =VLOOKUP(A106,'Dataset '!A:I,9,0) -> 51 - 100 | H106: 67 | I106: 4 | J106: 2500000 | K106: 2500000 | L106: =VLOOKUP($A106,'Dataset '!$A:$I,5,0) -> 45363 | M106: =J106/H106 -> 37313.433 | N106: =K106/H106 -> 37313.433 | O106: =J106/I106 -> 625000 | P106: =K106/J106 -> 1 | Q106: 16 | R106: 1 | S106: 1 | T106: 0 | U106: 0 | V106: 2 | W106: B2B
A107: Destaxa | B107: Brasil | C107: https://destaxa.com.br/ | D107: 2021 | E107: FinTech, Payments | F107: Seed | G107: =VLOOKUP(A107,'Dataset '!A:I,9,0) -> 51 - 100 | H107: 36 | I107: 4 | J107: 10300000 | K107: 6000000 | L107: =VLOOKUP($A107,'Dataset '!$A:$I,5,0) -> 45254 | M107: =J107/H107 -> 286111.11 | N107: =K107/H107 -> 166666.67 | O107: =J107/I107 -> 2575000 | P107: =K107/J107 -> 0.58252427 | Q107: 11 | R107: 0 | S107: 0 | T107: 1 | U107: 0 | V107: 1 | W107: B2B2C
A108: Beegol | B108: Brasil | C108: https://www.beegol.com/ | D108: 2019 | E108: AI, Telecom | F108: Venture | G108: =VLOOKUP(A108,'Dataset '!A:I,9,0) -> 51 - 100 | H108: 64 | I108: 6 | J108: 5600000 | K108: 1000000 | L108: =VLOOKUP($A108,'Dataset '!$A:$I,5,0) -> 45632 | M108: =J108/H108 -> 87500 | N108: =K108/H108 -> 15625 | O108: =J108/I108 -> 933333.33 | P108: =K108/J108 -> 0.17857143 | Q108: 25 | R108: 0 | S108: 1 | T108: 1 | U108: 0 | V108: 0 | W108: Unknown
A109: Culttivo | B109: Brasil | C109: http://www.culttivo.com | D109: 2020 | E109: AgTech, Coffee Credit | F109: Series A | G109: =VLOOKUP(A109,'Dataset '!A:I,9,0) -> 51 - 100 | H109: 65 | I109: 5 | J109: 16547191 | K109: 1000000 | L109: =VLOOKUP($A109,'Dataset '!$A:$I,5,0) -> 45981 | M109: =J109/H109 -> 254572.17 | N109: =K109/H109 -> 15384.615 | O109: =J109/I109 -> 3309438.2 | P109: =K109/J109 -> 0.060433218 | Q109: 17 | R109: 0 | S109: 0 | T109: 0 | U109: 0 | V109: 3 | W109: B2B
A110: Albato | B110: Portugal | C110: https://albato.com/ | D110: 2019 | E110: No-code, Automation, SaaS | F110: Seed | G110: =VLOOKUP(A110,'Dataset '!A:I,9,0) -> 11 - 50 | H110: 43 | I110: 6 | J110: 1000000 | K110: 1000000 | L110: =VLOOKUP($A110,'Dataset '!$A:$I,5,0) -> 44197 | M110: =J110/H110 -> 23255.814 | N110: =K110/H110 -> 23255.814 | O110: =J110/I110 -> 166666.67 | P110: =K110/J110 -> 1 | Q110: 24 | R110: 1 | S110: 1 | T110: 1 | U110: 1 | V110: 5 | W110: B2B
A111: Kamino | B111: Brasil | C111: https://kamino.com.br/ | D111: 2021 | E111: Financial OS, AI | F111: Series A | G111: =VLOOKUP(A111,'Dataset '!A:I,9,0) -> 51 - 100 | H111: 170 | I111: 4 | J111: 20170000 | K111: 10120000 | L111: =VLOOKUP($A111,'Dataset '!$A:$I,5,0) -> 45909 | M111: =J111/H111 -> 118647.06 | N111: =K111/H111 -> 59529.412 | O111: =J111/I111 -> 5042500 | P111: =K111/J111 -> 0.50173525 | Q111: 43 | R111: 1 | S111: 1 | T111: 4 | U111: 2 | V111: 3 | W111: B2B
A112: BotCity | B112: Brasil | C112: https://botcity.dev/ | D112: 2018 | E112: RPA, GenAI | F112: Series A | G112: =VLOOKUP(A112,'Dataset '!A:I,9,0) -> 51 - 100 | H112: 75 | I112: 7 | J112: 15000000 | K112: 12000000 | L112: =VLOOKUP($A112,'Dataset '!$A:$I,5,0) -> 45925 | M112: =J112/H112 -> 200000 | N112: =K112/H112 -> 160000 | O112: =J112/I112 -> 2142857.1 | P112: =K112/J112 -> 0.8 | Q112: 15 | R112: 2 | S112: 0 | T112: 2 | U112: 0 | V112: 1 | W112: B2B
A113: Stratio | B113: Portugal | C113: https://stratioautomotive.com/ | D113: 2017 | E113: Fleet Management | F113: Series A | G113: =VLOOKUP(A113,'Dataset '!A:I,9,0) -> 51 - 100 | H113: 67 | I113: 8 | J113: 15365459 | K113: 12000000 | L113: =VLOOKUP($A113,'Dataset '!$A:$I,5,0) -> 44529 | M113: =J113/H113 -> 229335.21 | N113: =K113/H113 -> 179104.48 | O113: =J113/I113 -> 1920682.4 | P113: =K113/J113 -> 0.78097244 | Q113: 29 | R113: 1 | S113: 1 | T113: 4 | U113: 0 | V113: 2 | W113: B2B
... A116: Traive | B116: Brasil | C116: https://traive.com.br/ | D116: 2018 | E116: AgFintech, GenAI | F116: Series B | G116: =VLOOKUP(A116,'Dataset '!A:I,9,0) -> 51 - 100 | H116: 55 | I116: 7 | J116: 50800000 | K116: 20000000 | L116: =VLOOKUP($A116,'Dataset '!$A:$I,5,0) -> 45324 | M116: =J116/H116 -> 923636.36 | N116: =K116/H116 -> 363636.36 | O116: =J116/I116 -> 7257142.9 | P116: =K116/J116 -> 0.39370079 | Q116: 27 | R116: 1 | S116: 0 | T116: 2 | U116: 1 | V116: 4 | W116: B2B
A117: Agrolend | B117: Brasil | C117: https://agrolend.agr.br/ | D117: 2020 | E117: AgFintech, Credit | F117: Series C | G117: =VLOOKUP(A117,'Dataset '!A:I,9,0) -> 51 - 100 | H117: 76 | I117: 5 | J117: 162578377 | K117: 3000000 | L117: =VLOOKUP($A117,'Dataset '!$A:$I,5,0) -> 45806 | M117: 2167711.69 | N117: =K117/H117 -> 39473.684 | O117: =J117/I117 -> 32515675 | P117: =K117/J117 -> 0.018452638 | Q117: 15 | R117: 2 | S117: 1 | T117: 1 | U117: 0 | V117: 0 | W117: B2B
A118: Akurateco | B118: Portugal | C118: https://akurateco.com/ | D118: 2019 | E118: Payments, SaaS | F118: Seed | G118: =VLOOKUP(A118,'Dataset '!A:I,9,0) -> 51 - 100 | H118: 60 | I118: 6 | J118: 406400 | K118: 300000 | L118: =VLOOKUP($A118,'Dataset '!$A:$I,5,0) -> 45078 | M118: 5418.67 | N118: =K118/H118 -> 5000 | O118: =J118/I118 -> 67733.333 | P118: =K118/J118 -> 0.73818898 | Q118: 55 | R118: 1 | S118: 5 | T118: 6 | U118: 0 | V118: 4 | W118: Unknown
A119: GuestCentric | B119: Portugal | C119: https://guestcentric.com/ | D119: 2006 | E119: Hotel Ecommerce, Travel | F119: Venture | G119: =VLOOKUP(A119,'Dataset '!A:I,9,0) -> 51 - 100 | H119: 56 | I119: 19 | J119: 5250000 | K119: 4000000 | L119: =VLOOKUP($A119,'Dataset '!$A:$I,5,0) -> 40008 | M119: 70000.0 | N119: =K119/H119 -> 71428.571 | O119: =J119/I119 -> 276315.79 | P119: =K119/J119 -> 0.76190476 | Q119: 22 | R119: 0 | S119: 0 | T119: 2 | U119: 0 | V119: 2 | W119: B2B
A120: Stark Bank | B120: Brasil | C120: https://starkbank.com | D120: 2018 | E120: Digital Bank B2B | F120: Series B | G120: =VLOOKUP(A120,'Dataset '!A:I,9,0) -> 51 - 100 | H120: 90 | I120: 7 | J120: 59956555 | K120: 45000000 | L120: =VLOOKUP($A120,'Dataset '!$A:$I,5,0) -> 44662 | M120: 799420.73 | N120: =K120/H120 -> 500000 | O120: =J120/I120 -> 8565222.1 | P120: =K120/J120 -> 0.75054346 | Q120: 36 | R120: 1 | S120: 1 | T120: 1 | U120: 3 | V120: 4 | W120: B2B
A121: Jscrambler | B121: Portugal | C121: https://jscrambler.com/ | D121: 2014 | E121: Cyber Security | F121: Venture | G121: =VLOOKUP(A121,'Dataset '!A:I,9,0) -> 51 - 100 | H121: 90 | I121: 11 | J121: 22500000 | K121: 5200000 | L121: =VLOOKUP($A121,'Dataset '!$A:$I,5,0) -> 45700 | M121: 300000.0 | N121: =K121/H121 -> 57777.778 | O121: =J121/I121 -> 2045454.5 | P121: =K121/J121 -> 0.23111111 | Q121: 27 | R121: 1 | S121: 2 | T121: 0 | U121: 1 | V121: 3 | W121: B2B
A122: BEMAGRO | B122: Brasil | C122: http://bemagro.com | D122: 2018 | E122: AgTech, AI | F122: Series A | G122: =VLOOKUP(A122,'Dataset '!A:I,9,0) -> 51 - 100 | H122: 75 | I122: 7 | J122: 10611877 | K122: 5800000 | L122: =VLOOKUP($A122,'Dataset '!$A:$I,5,0) -> 46067 | M122: 141491.69 | N122: =K122/H122 -> 77333.333 | O122: =J122/I122 -> 1515982.4 | P122: =K122/J122 -> 0.54655741 | Q122: 14 | R122: 2 | S122: 0 | T122: 1 | U122: 0 | V122: 2 | W122: B2B
A123: Tivita | B123: Brasil | C123: https://tivita.com/ | D123: 2023 | E123: HealthTech, SaaS | F123: Seed | G123: =VLOOKUP(A123,'Dataset '!A:I,9,0) -> 51 - 100 | H123: 56 | I123: 2 | J123: 6000000 | K123: 6000000 | L123: =VLOOKUP($A123,'Dataset '!$A:$I,5,0) -> 45475 | M123: 80000.0 | N123: =K123/H123 -> 107142.86 | O123: =J123/I123 -> 3000000 | P123: =K123/J123 -> 1 | Q123: 32 | R123: 1 | S123: 1 | T123: 1 | U123: 3 | V123: 3 | W123: B2B
A124: Musiversal | B124: Portugal | C124: https://musiversal.com/ | D124: 2018 | E124: Music, Marketplace | F124: Series A | G124: =VLOOKUP(A124,'Dataset '!A:I,9,0) -> 51 - 100 | H124: 73 | I124: 7 | J124: 12134606 | K124: 6000000 | L124: =VLOOKUP($A124,'Dataset '!$A:$I,5,0) -> 45910 | M124: 161794.75 | N124: =K124/H124 -> 82191.781 | O124: =J124/I124 -> 1733515.1 | P124: =K124/J124 -> 0.49445363 | Q124: 23 | R124: 1 | S124: 3 | T124: 2 | U124: 0 | V124: 3 | W124: B2B2C
A125: Barte | B125: Brasil | C125: https://www.barte.com/ | D125: 2021 | E125: B2B Payments | F125: Series A | G125: =VLOOKUP(A125,'Dataset '!A:I,9,0) -> 51 - 100 | H125: 110 | I125: 4 | J125: 12200000 | K125: 8000000 | L125: =VLOOKUP($A125,'Dataset '!$A:$I,5,0) -> 45569 | M125: 162666.67 | N125: =K125/H125 -> 72727.273 | O125: =J125/I125 -> 3050000 | P125: =K125/J125 -> 0.6557377 | Q125: 24 | R125: 0 | S125: 1 | T125: 0 | U125: 0 | V125: 4 | W125: B2B2C
A126: OurSupport | B126: Portugal | C126: oursupport.co | D126: 2018 | E126: IT Support, Platform | F126: Series A | G126: =VLOOKUP(A126,'Dataset '!A:I,9,0) -> 51 - 100 | H126: 60 | I126: 7 | J126: 2219400 | K126: 1404000 | L126: =VLOOKUP($A126,'Dataset '!$A:$I,5,0) -> 45747 | M126: 29592.0 | N126: =K126/H126 -> 23400 | O126: =J126/I126 -> 317057.14 | P126: =K126/J126 -> 0.63260341 | Q126: 8 | R126: 0 | S126: 0 | T126: 2 | U126: 0 | V126: 0 | W126: B2B2C
A127: Wegho | B127: Portugal | C127: https://www.wegho.com/ | D127: 2017 | E127: Home Services, Digital | F127: Seed | G127: =VLOOKUP(A127,'Dataset '!A:I,9,0) -> 51 - 100 | H127: 51 | I127: 8 | J127: 1836000 | K127: 1836000 | L127: =VLOOKUP($A127,'Dataset '!$A:$I,5,0) -> 43411 | M127: 24480.0 | N127: =K127/H127 -> 36000 | O127: =J127/I127 -> 229500 | P127: =K127/J127 -> 1 | Q127: 26 | R127: 0 | S127: 1 | T127: 4 | U127: 2 | V127: 4 | W127: B2C
A128: Lyzer | B128: Portugal | C128: https://www.lyzer.tech/ | D128: 2024 | E128: E-Commerce, Delivery | F128: Venture | G128: =VLOOKUP(A128,'Dataset '!A:I,9,0) -> 51 - 100 | H128: 66 | I128: 1 | J128: 11934000 | K128: 10800000 | L128: =VLOOKUP($A128,'Dataset '!$A:$I,5,0) -> 45799 | M128: 159120.0 | N128: =K128/H128 -> 163636.36 | O128: =J128/I128 -> 11934000 | P128: =K128/J128 -> 0.90497738 | Q128: 17 | R128: 0 | S128: 0 | T128: 1 | U128: 0 | V128: 1 | W128: B2C
... A153: Nagro | B153: Brasil | C153: http://nagro.com.br/ | D153: 2016 | E153: AgFintech, Big Data | F153: Series B | G153: =VLOOKUP(A153,'Dataset '!A:I,9,0) -> 51 - 100 | H153: 76 | I153: 9 | J153: 59726979 | K153: 9000000 | L153: =VLOOKUP($A153,'Dataset '!$A:$I,5,0) -> 46043 | M153: 796359.72 | N153: =K153/H153 -> 118421.05 | O153: =J153/I153 -> 6636331 | P153: =K153/J153 -> 0.15068567 | Q153: 25 | R153: 1 | S153: 0 | T153: 0 | U153: 0 | V153: 4 | W153: B2B
A154: Avenidas | B154: Portugal | C154: http://www.avenidas.pt | D154: 2016 | E154: Mobility, Transportation | F154: Venture | G154: =VLOOKUP(A154,'Dataset '!A:I,9,0) -> 101 - 250 | H154: 85 | I154: 9 | J154: 108000 | K154: 108000 | L154: =VLOOKUP($A154,'Dataset '!$A:$I,5,0) -> 45027 | M154: =J154/H154 -> 1270.5882 | N154: =K154/H154 -> 1270.5882 | O154: =J154/I154 -> 12000 | P154: =K154/J154 -> 1 | Q154: 13 | R154: 0 | S154: 1 | T154: 0 | U154: 0 | V154: 1 | W154: B2B2C
A155: Pitzi | B155: Brasil | C155: http://www.pitzi.com.br | D155: 2012 | E155: InsurTech | F155: Series D | G155: =VLOOKUP(A155,'Dataset '!A:I,9,0) -> 101 - 250 | H155: 200 | I155: 13 | J155: 29700000 | K155: 10300000 | L155: =VLOOKUP($A155,'Dataset '!$A:$I,5,0) -> 43773 | M155: =J155/H155 -> 148500 | N155: =K155/H155 -> 51500 | O155: =J155/I155 -> 2284615.4 | P155: =K155/J155 -> 0.34680135 | Q155: 26 | R155: 1 | S155: 1 | T155: 3 | U155: 2 | V155: 2 | W155: B2B
A156: Farmtech | B156: Brasil | C156: https://farmtech.com.br/ | D156: 2017 | E156: Asset Mgmt, Agri | F156: Venture | G156: =VLOOKUP(A156,'Dataset '!A:I,9,0) -> 101 - 250 | H156: 175 | I156: 8 | J156: 10000000 | K156: 10000000 | L156: =VLOOKUP($A156,'Dataset '!$A:$I,5,0) -> 45483 | M156: =J156/H156 -> 57142.857 | N156: =K156/H156 -> 57142.857 | O156: =J156/I156 -> 1250000 | P156: =K156/J156 -> 1 | Q156: 0 | R156: 0 | S156: 0 | T156: 0 | U156: 0 | V156: 0 | W156: Unknown
A157: Monkey | B157: Brasil | C157: https://www.monkey.tech | D157: 2016 | E157: FinTech, Finance | F157: Series B | G157: =VLOOKUP(A157,'Dataset '!A:I,9,0) -> 501 - 1000 | H157: 590 | I157: 9 | J157: 19600000 | K157: 12100000 | L157: =VLOOKUP($A157,'Dataset '!$A:$I,5,0) -> 45485 | M157: =J157/H157 -> 33220.339 | N157: =K157/H157 -> 20508.475 | O157: =J157/I157 -> 2177777.8 | P157: =K157/J157 -> 0.61734694 | Q157: 27 | R157: 0 | S157: 0 | T157: 1 | U157: 0 | V157: 5 | W157: B2B
A158: Zak | B158: Brasil | C158: https://www.zak.app/ | D158: 2018 | E158: FinTech, Food | F158: Series A | G158: =VLOOKUP(A158,'Dataset '!A:I,9,0) -> 101 - 250 | H158: 180 | I158: 7 | J158: 15000000 | K158: 15000000 | L158: =VLOOKUP($A158,'Dataset '!$A:$I,5,0) -> 44510 | M158: =J158/H158 -> 83333.333 | N158: =K158/H158 -> 83333.333 | O158: =J158/I158 -> 2142857.1 | P158: =K158/J158 -> 1 | Q158: 16 | R158: 0 | S158: 1 | T158: 1 | U158: 1 | V158: 3 | W158: B2B2C
A159: Quanto | B159: Brasil | C159: quan.to | D159: 2016 | E159: Open Banking | F159: Series A | G159: =VLOOKUP(A159,'Dataset '!A:I,9,0) -> 101 - 250 | H159: 150 | I159: 9 | J159: 20000000 | K159: 15000000 | L159: =VLOOKUP($A159,'Dataset '!$A:$I,5,0) -> 44091 | M159: =J159/H159 -> 133333.33 | N159: =K159/H159 -> 100000 | O159: =J159/I159 -> 2222222.2 | P159: =K159/J159 -> 0.75 | Q159: 0 | R159: 0 | S159: 0 | T159: 0 | U159: 0 | V159: 0 | W159: B2B
A160: Konsi | B160: Brasil | C160: https://www.konsi.com.br/ | D160: 2021 | E160: FinTech, Payroll Loans | F160: Seed | G160: =VLOOKUP(A160,'Dataset '!A:I,9,0) -> 101 - 250 | H160: 150 | I160: 4 | J160: 1611770 | K160: 1000000 | L160: =VLOOKUP($A160,'Dataset '!$A:$I,5,0) -> 45467 | M160: =J160/H160 -> 10745.133 | N160: =K160/H160 -> 6666.6667 | O160: =J160/I160 -> 402942.5 | P160: =K160/J160 -> 0.62043592 | Q160: 25 | R160: 0 | S160: 0 | T160: 0 | U160: 2 | V160: 5 | W160: B2B2C
A161: Nutrium | B161: Portugal | C161: https://nutrium.com/ | D161: 2015 | E161: Health, Nutrition | F161: Series A | G161: =VLOOKUP(A161,'Dataset '!A:I,9,0) -> 101 - 250 | H161: 200 | I161: 10 | J161: 19935543 | K161: 12000000 | L161: =VLOOKUP($A161,'Dataset '!$A:$I,5,0) -> 45916 | M161: =J161/H161 -> 99677.715 | N161: =K161/H161 -> 60000 | O161: =J161/I161 -> 1993554.3 | P161: =K161/J161 -> 0.60193996 | Q161: 36 | R161: 1 | S161: 0 | T161: 2 | U161: 2 | V161: 6 | W161: B2B
A162: Nonius | B162: Portugal | C162: https://noniussolutions.com/ | D162: 2025 | E162: Cloud Infrastructure | F162: Venture | G162: =VLOOKUP(A162,'Dataset '!A:I,9,0) -> 101 - 250 | H162: 240 | I162: 0 | J162: 12960000 | K162: 11880000 | L162: =VLOOKUP($A162,'Dataset '!$A:$I,5,0) -> 42987 | M162: =J162/H162 -> 54000 | N162: =K162/H162 -> 49500 | O162: =J162/I162 -> #DIV/0! | P162: =K162/J162 -> 0.91666667 | Q162: 39 | R162: 2 | S162: 0 | T162: 2 | U162: 2 | V162: 2 | W162: B2B
A163: Arado | B163: Brasil | C163: http://sobre.arado.com.br | D163: 2021 | E163: AgTech, Supply Chain | F163: Series B | G163: =VLOOKUP(A163,'Dataset '!A:I,9,0) -> 101 - 250 | H163: 175 | I163: 4 | J163: 21370375 | K163: 2000000 | L163: =VLOOKUP($A163,'Dataset '!$A:$I,5,0) -> 45625 | M163: =J163/H163 -> 122116.43 | N163: =K163/H163 -> 11428.571 | O163: =J163/I163 -> 5342593.8 | P163: =K163/J163 -> 0.093587501 | Q163: 7 | R163: 0 | S163: 0 | T163: 0 | U163: 0 | V163: 1 | W163: B2C
A164: 180 Seguros | B164: Brasil | C164: https://180s.com.br | D164: 2020 | E164: InsurTech | F164: Venture | G164: =VLOOKUP(A164,'Dataset '!A:I,9,0) -> 101 - 250 | H164: 140 | I164: 5 | J164: 51118155 | K164: 2500000 | L164: =VLOOKUP($A164,'Dataset '!$A:$I,5,0) -> 45953 | M164: =J164/H164 -> 365129.68 | N164: =K164/H164 -> 17857.143 | O164: =J164/I164 -> 10223631 | P164: =K164/J164 -> 0.048906303 | Q164: 44 | R164: 0 | S164: 2 | T164: 3 | U164: 0 | V164: 2 | W164: B2B2C
A165: SWAP | B165: Brasil | C165: https://www.swap.financial/ | D165: 2018 | E165: FinTech Partner | F165: Series A | G165: =VLOOKUP(A165,'Dataset '!A:I,9,0) -> 101 - 250 | H165: 230 | I165: 7 | J165: 28300000 | K165: 25000000 | L165: =VLOOKUP($A165,'Dataset '!$A:$I,5,0) -> 44497 | M165: =J165/H165 -> 123043.48 | N165: =K165/H165 -> 108695.65 | O165: =J165/I165 -> 4042857.1 | P165: =K165/J165 -> 0.88339223 | Q165: 29 | R165: 1 | S165: 1 | T165: 1 | U165: 2 | V165: 4 | W165: B2B
... A167: Capim | B167: Brasil | C167: http://www.capim.com.br | D167: 2021 | E167: Health Tech, BNPL | F167: Series A | G167: =VLOOKUP(A167,'Dataset '!A:I,9,0) -> 101 - 250 | H167: 130 | I167: 4 | J167: 26700000 | K167: 26700000 | L167: =VLOOKUP($A167,'Dataset '!$A:$I,5,0) -> 45714 | M167: =J167/H167 -> 205384.62 | N167: =K167/H167 -> 205384.62 | O167: =J167/I167 -> 6675000 | P167: =K167/J167 -> 1 | Q167: 13 | R167: 0 | S167: 0 | T167: 0 | U167: 0 | V167: 3 | W167: B2B
A168: Kanastra | B168: Brasil | C168: www.kanastra.com.br | D168: 2022 | E168: Alternative Inv. | F168: Series B | G168: =VLOOKUP(A168,'Dataset '!A:I,9,0) -> 101 - 250 | H168: 230 | I168: 3 | J168: 63748062 | K168: 30000000 | L168: =VLOOKUP($A168,'Dataset '!$A:$I,5,0) -> 45931 | M168: 364274.64 | N168: =K168/H168 -> 130434.78 | O168: =J168/I168 -> 21249354 | P168: =K168/J168 -> 0.47060254 | Q168: 44 | R168: 0 | S168: 3 | T168: 5 | U168: 1 | V168: 2 | W168: B2B
A169: Enter | B169: Brasil | C169: https://www.getenter.ai/ | D169: 2023 | E169: Legal Tech, AI | F169: Series A | G169: =VLOOKUP(A169,'Dataset '!A:I,9,0) -> 101 - 250 | H169: 130 | I169: 2 | J169: 40500000 | K169: 35000000 | L169: =VLOOKUP($A169,'Dataset '!$A:$I,5,0) -> 45923 | M169: 231428.57 | N169: =K169/H169 -> 269230.77 | O169: =J169/I169 -> 20250000 | P169: =K169/J169 -> 0.86419753 | Q169: 12 | R169: 0 | S169: 1 | T169: 0 | U169: 1 | V169: 0 | W169: B2B
A170: Inventa | B170: Brasil | C170: https://inventa.com.br/ | D170: 2021 | E170: Wholesale B2B | F170: Series B | G170: =VLOOKUP(A170,'Dataset '!A:I,9,0) -> 101 - 250 | H170: 98 | I170: 4 | J170: 80358865 | K170: 55000000 | L170: =VLOOKUP($A170,'Dataset '!$A:$I,5,0) -> 44678 | M170: 459193.51 | N170: =K170/H170 -> 561224.49 | O170: =J170/I170 -> 20089716 | P170: =K170/J170 -> 0.68442978 | Q170: 6 | R170: 0 | S170: 0 | T170: 0 | U170: 0 | V170: 0 | W170: B2B2C
A171: Eneida | B171: Portugal | C171: https://eneida.io/ | D171: 2012 | E171: AI, Power Grid | F171: Series B | G171: =VLOOKUP(A171,'Dataset '!A:I,9,0) -> 101 - 250 | H171: 120 | I171: 13 | J171: 17442000 | K171: 11340000 | L171: =VLOOKUP($A171,'Dataset '!$A:$I,5,0) -> 45478 | M171: 99668.57 | N171: =K171/H171 -> 94500 | O171: =J171/I171 -> 1341692.3 | P171: =K171/J171 -> 0.6501548 | Q171: 17 | R171: 0 | S171: 0 | T171: 2 | U171: 1 | V171: 1 | W171: B2B2C
A172: Infraspeak | B172: Portugal | C172: https://infraspeak.com/pt-br | D172: 2015 | E172: Facility Mgmt, SaaS | F172: Series B | G172: =VLOOKUP(A172,'Dataset '!A:I,9,0) -> 101 - 250 | H172: 250 | I172: 10 | J172: 39410667 | K172: 19440000 | L172: =VLOOKUP($A172,'Dataset '!$A:$I,5,0) -> 45594 | M172: 225203.81 | N172: =K172/H172 -> 77760 | O172: =J172/I172 -> 3941066.7 | P172: =K172/J172 -> 0.49326747 | Q172: 38 | R172: 0 | S172: 0 | T172: 3 | U172: 2 | V172: 6 | W172: B2B
A173: Automaise | B173: Portugal | C173: https://www.automaise.com/ | D173: 2017 | E173: AI, Customer Service | F173: Series A | G173: =VLOOKUP(A173,'Dataset '!A:I,9,0) -> 101 - 250 | H173: 66 | I173: 8 | J173: 6480000 | K173: 5400000 | L173: =VLOOKUP($A173,'Dataset '!$A:$I,5,0) -> 45740 | M173: 37028.57 | N173: =K173/H173 -> 81818.182 | O173: =J173/I173 -> 810000 | P173: =K173/J173 -> 0.83333333 | Q173: 39 | R173: 2 | S173: 1 | T173: 4 | U173: 2 | V173: 2 | W173: B2B
A174: Provu | B174: Brasil | C174: https://provu.com.br/ | D174: 2015 | E174: FinTech, Banking | F174: Venture | G174: =VLOOKUP(A174,'Dataset '!A:I,9,0) -> 11 - 50 | H174: 36 | I174: 10 | J174: 252000000 | K174: 252000000 | L174: =VLOOKUP($A174,'Dataset '!$A:$I,5,0) -> 44517 | M174: 1440000.0 | N174: =K174/H174 -> 7000000 | O174: =J174/I174 -> 25200000 | P174: =K174/J174 -> 1 | Q174: 5 | R174: 0 | S174: 1 | T174: 1 | U174: 0 | V174: 0 | W174: B2B2C
A175: Colmeia | B175: Brasil | C175: https://colmeia.cx/ | D175: 2019 | E175: SaaS, Telecom | F175: Venture | G175: =VLOOKUP(A175,'Dataset '!A:I,9,0) -> 101 - 250 | H175: 120 | I175: 6 | J175: 8100000 | K175: 3240000 | L175: =VLOOKUP($A175,'Dataset '!$A:$I,5,0) -> 45985 | M175: 46285.71 | N175: =K175/H175 -> 27000 | O175: =J175/I175 -> 1350000 | P175: =K175/J175 -> 0.4 | Q175: 25 | R175: 0 | S175: 1 | T175: 3 | U175: 0 | V175: 3 | W175: B2B
A176: OmniChat | B176: Brasil | C176: https://omni.chat/ | D176: 2016 | E176: Conv. Commerce | F176: Seed | G176: =VLOOKUP(A176,'Dataset '!A:I,9,0) -> 101 - 250 | H176: 94 | I176: 9 | J176: 12600000 | K176: 9000000 | L176: =VLOOKUP($A176,'Dataset '!$A:$I,5,0) -> 45810 | M176: 72000.0 | N176: =K176/H176 -> 95744.681 | O176: =J176/I176 -> 1400000 | P176: =K176/J176 -> 0.71428571 | Q176: 27 | R176: 0 | S176: 0 | T176: 0 | U176: 2 | V176: 5 | W176: B2B2C
A177: Darwin Seguros | B177: Brasil | C177: https://www.darwinseguros.com/ | D177: 2021 | E177: InsurTech, Auto | F177: Series B | G177: =VLOOKUP(A177,'Dataset '!A:I,9,0) -> 101 - 250 | H177: 100 | I177: 4 | J177: 28980000 | K177: 18360000 | L177: =VLOOKUP($A177,'Dataset '!$A:$I,5,0) -> 45953 | M177: 165600.0 | N177: =K177/H177 -> 183600 | O177: =J177/I177 -> 7245000 | P177: =K177/J177 -> 0.63354037 | Q177: 40 | R177: 1 | S177: 9 | T177: 4 | U177: 0 | V177: 3 | W177: B2B2C
A178: Arvo | B178: Brasil | C178: https://www.arvo.com.br/ | D178: 2022 | E178: Health Tech, AI | F178: Series A | G178: =VLOOKUP(A178,'Dataset '!A:I,9,0) -> 101 - 250 | H178: 110 | I178: 3 | J178: 24457449 | K178: 19080000 | L178: =VLOOKUP($A178,'Dataset '!$A:$I,5,0) -> 45917 | M178: 139756.85 | N178: =K178/H178 -> 173454.55 | O178: =J178/I178 -> 8152483 | P178: =K178/J178 -> 0.78013042 | Q178: 22 | R178: 0 | S178: 3 | T178: 0 | U178: 2 | V178: 2 | W178: B2B
A179: Onze | B179: Brasil | C179: http://www.onze.com.br | D179: 2020 | E179: PensionTech, FinTech | F179: Series A | G179: =VLOOKUP(A179,'Dataset '!A:I,9,0) -> 101 - 250 | H179: 160 | I179: 5 | J179: 29340000 | K179: 19800000 | L179: =VLOOKUP($A179,'Dataset '!$A:$I,5,0) -> 45629 | M179: 167657.14 | N179: =K179/H179 -> 123750 | O179: =J179/I179 -> 5868000 | P179: =K179/J179 -> 0.67484663 | Q179: 28 | R179: 0 | S179: 1 | T179: 1 | U179: 3 | V179: 4 | W179: B2B
... A187: Sensei | B187: Portugal | C187: https://www.sensei.tech/ | D187: 2017 | E187: AI, Retail Tech | F187: Series A | G187: =VLOOKUP(A187,'Dataset '!A:I,9,0) -> 101 - 250 | H187: 120 | I187: 8 | J187: 23368167 | K187: 16380000 | L187: =VLOOKUP($A187,'Dataset '!$A:$I,5,0) -> 45587 | M187: 133532.38 | N187: =K187/H187 -> 136500 | O187: =J187/I187 -> 2921020.9 | P187: =K187/J187 -> 0.70095357 | Q187: 29 | R187: 1 | S187: 5 | T187: 1 | U187: 2 | V187: 0 | W187: B2B
A188: Accountfy | B188: Brasil | C188: https://www.accountfy.com/ | D188: 2017 | E188: SaaS, Fin. Mgmt | F188: Series A | G188: =VLOOKUP(A188,'Dataset '!A:I,9,0) -> 251 - 500 | H188: 320 | I188: 8 | J188: 11000000 | K188: 4500000 | L188: =VLOOKUP($A188,'Dataset '!$A:$I,5,0) -> 44364 | M188: =J188/H188 -> 34375 | N188: =K188/H188 -> 14062.5 | O188: =J188/I188 -> 1375000 | P188: =K188/J188 -> 0.40909091 | Q188: 24 | R188: 1 | S188: 0 | T188: 1 | U188: 1 | V188: 4 | W188: B2B
A189: Sympla | B189: Brasil | C189: https://produtores.sympla.com.br/ | D189: 2012 | E189: Events, Ticketing | F189: Venture | G189: =VLOOKUP(A189,'Dataset '!A:I,9,0) -> 251 - 500 | H189: 460 | I189: 13 | J189: 8800000 | K189: 4800000 | L189: =VLOOKUP($A189,'Dataset '!$A:$I,5,0) -> 43069 | M189: =J189/H189 -> 19130.435 | N189: =K189/H189 -> 10434.783 | O189: =J189/I189 -> 676923.08 | P189: =K189/J189 -> 0.54545455 | Q189: 119 | R189: 0 | S189: 14 | T189: 6 | U189: 9 | V189: 9 | W189: B2B2C
A190: Frente | B190: Brasil | C190: https://frentecorretora.com.br/ | D190: 2018 | E190: FinTech, FX | F190: Series A | G190: =VLOOKUP(A190,'Dataset '!A:I,9,0) -> 251 - 500 | H190: 270 | I190: 7 | J190: 6000000 | K190: 5500000 | L190: =VLOOKUP($A190,'Dataset '!$A:$I,5,0) -> 45825 | M190: =J190/H190 -> 22222.222 | N190: =K190/H190 -> 20370.37 | O190: =J190/I190 -> 857142.86 | P190: =K190/J190 -> 0.91666667 | Q190: 10 | R190: 1 | S190: 0 | T190: 1 | U190: 0 | V190: 1 | W190: Unknown
A191: Sami | B191: Brasil | C191: https://www.samisaude.com.br/ | D191: 2018 | E191: Health Tech | F191: Series B | G191: =VLOOKUP(A191,'Dataset '!A:I,9,0) -> 251 - 500 | H191: 490 | I191: 7 | J191: 66231000 | K191: 10000000 | L191: =VLOOKUP($A191,'Dataset '!$A:$I,5,0) -> 45643 | M191: =J191/H191 -> 135165.31 | N191: =K191/H191 -> 20408.163 | O191: =J191/I191 -> 9461571.4 | P191: =K191/J191 -> 0.1509867 | Q191: 24 | R191: 1 | S191: 1 | T191: 0 | U191: 0 | V191: 4 | W191: B2B2C
A192: Genial Care | B192: Brasil | C192: https://genialcare.com.br/ | D192: 2020 | E192: HealthTech, Autism | F192: Venture | G192: =VLOOKUP(A192,'Dataset '!A:I,9,0) -> 251 - 500 | H192: 150 | I192: 5 | J192: 31005209 | K192: 10000000 | L192: =VLOOKUP($A192,'Dataset '!$A:$I,5,0) -> 45316 | M192: =J192/H192 -> 206701.39 | N192: =K192/H192 -> 66666.667 | O192: =J192/I192 -> 6201041.8 | P192: =K192/J192 -> 0.32252645 | Q192: 15 | R192: 0 | S192: 0 | T192: 0 | U192: 0 | V192: 3 | W192: B2B2C
A193: Gringo | B193: Brasil | C193: https://gringo.com.vc/ | D193: 2019 | E193: Car App, Fintech | F193: Series C | G193: =VLOOKUP(A193,'Dataset '!A:I,9,0) -> 251 - 500 | H193: 375 | I193: 6 | J193: 90268052 | K193: 12500000 | L193: =VLOOKUP($A193,'Dataset '!$A:$I,5,0) -> 45544 | M193: =J193/H193 -> 240714.81 | N193: =K193/H193 -> 33333.333 | O193: =J193/I193 -> 15044675 | P193: =K193/J193 -> 0.13847646 | Q193: 26 | R193: 0 | S193: 0 | T193: 5 | U193: 1 | V193: 1 | W193: Unknown
A194: Celcoin | B194: Brasil | C194: https://www.celcoin.com.br/ | D194: 2016 | E194: FinTech, Payments | F194: Series C | G194: =VLOOKUP(A194,'Dataset '!A:I,9,0) -> 251 - 500 | H194: 440 | I194: 9 | J194: 156130284 | K194: 125000000 | L194: =VLOOKUP($A194,'Dataset '!$A:$I,5,0) -> 45461 | M194: =J194/H194 -> 354841.55 | N194: =K194/H194 -> 284090.91 | O194: =J194/I194 -> 17347809 | P194: =K194/J194 -> 0.80061342 | Q194: 85 | R194: 0 | S194: 5 | T194: 7 | U194: 4 | V194: 6 | W194: B2B
A195: Musa | B195: Brasil | C195: https://www.musa.co/ | D195: 2019 | E195: Waste Mgmt, B2B | F195: Series A | G195: =VLOOKUP(A195,'Dataset '!A:I,9,0) -> 251 - 500 | H195: 340 | I195: 6 | J195: 18500000 | K195: 15000000 | L195: =VLOOKUP($A195,'Dataset '!$A:$I,5,0) -> 44470 | M195: =J195/H195 -> 54411.765 | N195: =K195/H195 -> 44117.647 | O195: =J195/I195 -> 3083333.3 | P195: =K195/J195 -> 0.81081081 | Q195: 12 | R195: 0 | S195: 0 | T195: 1 | U195: 1 | V195: 2 | W195: Unknown
A196: UME | B196: Brasil | C196: https://ume.com.br/ | D196: 2019 | E196: FinTech, Credit | F196: Series B | G196: =VLOOKUP(A196,'Dataset '!A:I,9,0) -> 251 - 500 | H196: 360 | I196: 6 | J196: 86290928 | K196: 21000000 | L196: =VLOOKUP($A196,'Dataset '!$A:$I,5,0) -> 45908 | M196: =J196/H196 -> 239697.02 | N196: =K196/H196 -> 58333.333 | O196: =J196/I196 -> 14381821 | P196: =K196/J196 -> 0.24336278 | Q196: 18 | R196: 0 | S196: 0 | T196: 1 | U196: 4 | V196: 0 | W196: B2B2C
A197: Cayena | B197: Brasil | C197: https://cayena.com/ | D197: 2019 | E197: B2B Marketplace, Food | F197: Series B | G197: =VLOOKUP(A197,'Dataset '!A:I,9,0) -> 251 - 500 | H197: 410 | I197: 6 | J197: 89550000 | K197: 55000000 | L197: =VLOOKUP($A197,'Dataset '!$A:$I,5,0) -> 45503 | M197: 238800.0 | N197: =K197/H197 -> 134146.34 | O197: =J197/I197 -> 14925000 | P197: =K197/J197 -> 0.61418202 | Q197: 33 | R197: 0 | S197: 1 | T197: 1 | U197: 3 | V197: 4 | W197: B2B2C
A198: QI Tech | B198: Brasil | C198: https://qitech.com.br/ | D198: 2018 | E198: Banking-as-a-Service | F198: Series B | G198: =VLOOKUP(A198,'Dataset '!A:I,9,0) -> 251 - 500 | H198: 440 | I198: 7 | J198: 375000000 | K198: 63000000 | L198: =VLOOKUP($A198,'Dataset '!$A:$I,5,0) -> 45869 | M198: 1000000.0 | N198: =K198/H198 -> 143181.82 | O198: =J198/I198 -> 53571429 | P198: =K198/J198 -> 0.168 | Q198: 28 | R198: 0 | S198: 2 | T198: 3 | U198: 1 | V198: 3 | W198: B2B2C
A199: Bloq.it | B199: Portugal | C199: https://www.bloq.it/ | D199: 2019 | E199: IoT, Logistics | F199: Series B | G199: =VLOOKUP(A199,'Dataset '!A:I,9,0) -> 251 - 500 | H199: 350 | I199: 6 | J199: 31860000 | K199: 30240000 | L199: =VLOOKUP($A199,'Dataset '!$A:$I,5,0) -> 45805 | M199: 84960.0 | N199: =K199/H199 -> 86400 | O199: =J199/I199 -> 5310000 | P199: =K199/J199 -> 0.94915254 | Q199: 39 | R199: 1 | S199: 0 | T199: 6 | U199: 5 | V199: 0 | W199: B2B2C
A200: Amicci | B200: Brasil | C200: https://www.amicci.com.br/ | D200: 2015 | E200: RetailTech, SaaS | F200: Series A | G200: =VLOOKUP(A200,'Dataset '!A:I,9,0) -> 251 - 500 | H200: 260 | I200: 10 | J200: 7200000 | K200: 7200000 | L200: =VLOOKUP($A200,'Dataset '!$A:$I,5,0) -> 44823 | M200: 19200.0 | N200: =K200/H200 -> 27692.308 | O200: =J200/I200 -> 720000 | P200: =K200/J200 -> 1 | Q200: 26 | R200: 1 | S200: 0 | T200: 0 | U200: 2 | V200: 2 | W200: B2C
A201: Gênica | B201: Brasil | C201: https://genica.com.br/ | D201: 2015 | E201: AgTech, BioTech | F201: Venture | G201: =VLOOKUP(A201,'Dataset '!A:I,9,0) -> 251 - 500 | H201: 290 | I201: 10 | J201: 19300000 | K201: 12240000 | L201: =VLOOKUP($A201,'Dataset '!$A:$I,5,0) -> 45474 | M201: 51466.67 | N201: =K201/H201 -> 42206.897 | O201: =J201/I201 -> 1930000 | P201: =K201/J201 -> 0.63419689 | Q201: 19 | R201: 0 | S201: 0 | T201: 1 | U201: 0 | V201: 1 | W201: B2B
...

Sheet Definições
A1: Deeptech — tecnologias de alto conteúdo científico ou técnico: AI, IoT, Blockchain, Computer Vision, NLP, Biotech, Quantum. Um score alto aqui sinaliza que a empresa tem produto de maior complexidade técnica e barreira de entrada.
A3: Cloud Native — infraestrutura moderna: Kubernetes, Docker, Terraform, AWS, Prometheus, Snowflake. Sinaliza maturidade de engenharia e capacidade de escalar. Empresas em estágio inicial tendem a ter score baixo aqui.
A5: DevTools — linguagens e ferramentas de desenvolvimento: Python, React, Node.js, PostgreSQL, Git, GitLab. Sinaliza o tamanho e sofisticação do time de produto.
A7: Analytics — ferramentas de dados e monitoramento: Mixpanel, Datadog, Google Analytics, Amplitude, PowerBI. Sinaliza cultura data-driven — empresas que medem o que fazem.
A9: Growth Stack — ferramentas de vendas e marketing: HubSpot, Salesforce, Braze, Zendesk, LinkedIn Ads. Sinaliza que a empresa já está em modo de crescimento comercial ativo.

Sheet Critérios
A1: Startups | C1: Deeptech — tecnologias de alto conteúdo científico ou técnico: AI, IoT, Blockchain, Computer Vision, NLP, Biotech, Quantum. Um score alto aqui sinaliza que a empresa tem produto de maior complexidade técnica e barreira de entrada.
A2: Ativas
A3: Com pelo menos uma rodada de investimento conhecida | C3: Cloud Native — infraestrutura moderna: Kubernetes, Docker, Terraform, AWS, Prometheus, Snowflake. Sinaliza maturidade de engenharia e capacidade de escalar. Empresas em estágio inicial tendem a ter score baixo aqui.
A4: Não realizaram IPO
C5: DevTools — linguagens e ferramentas de desenvolvimento: Python, React, Node.js, PostgreSQL, Git, GitLab. Sinaliza o tamanho e sofisticação do time de produto.
C7: Analytics — ferramentas de dados e monitoramento: Mixpanel, Datadog, Google Analytics, Amplitude, PowerBI. Sinaliza cultura data-driven — empresas que medem o que fazem.
C9: Growth Stack — ferramentas de vendas e marketing: HubSpot, Salesforce, Braze, Zendesk, LinkedIn Ads. Sinaliza que a empresa já está em modo de crescimento comercial ativo.

Sheet Apoio
A1: Faixa
A2: 251-500 | B2: 251-500
A3: 11-50 | B3: 11-50
A4: 51-100 | B4: 51-100
A5: 5k-10k | B5: 5k-10k
A6: 1k-5k | B6: 1k-5k
A7: 10k+ | B7: 10k+
A8: 501-1000 | B8: 501-1000
A9: 101-250 | B9: 101-250
A10: 501-1k | B10: 501-1000
A11: 1001-5000 | B11: 1k-5k
A12: 10001+ | B12: 10k+
A13: 1001-5k | B13: 1k-5k
A14: 5001-10k | B14: 5k-10k
